Workbook

Sheet PDF_Stats
A1: Statement ID | B1: PDF Link | C1: Type | D1: Countries | E1: Trademarks | F1: AnnualRevenue | G1: Entities | H1: IndustrySectors | I1: OverseasObligations | J1: Number Of Pages | K1: Scan Rate | L1: Words per Page (Median) | M1: Status | N1: Number Of Pages | O1: Scan Rate | P1: Words per Page (Median) | Q1: Status
A2: 12 | B2: https://modernslaveryregister.gov.au/statements/12/ | C2: =VLOOKUP($A2,Sheet1!$A$2:$I$6793,2,FALSE) -> Joint | D2: =VLOOKUP($A2,Sheet1!$A$2:$I$6793,3,FALSE) -> Australia | E2: QinetiQ Pty Ltd | F2: 100-150M | G2: Qinetiq Pty Ltd (68 125 805 647) | J2: 7 | K2: 0.28571429 | L2: 514 | M2: =IF($K2 < 0.15, "Not Scanned",IF($K2 < 0.55, "Partially Scanned",IF($K2 >= 0.55, "Fully Scanned","Not Found"))) -> Partially Scanned | N2: 7 | O2: 0.28571429 | P2: 514 | Q2: =IF($K2 < 0.15, "Not Scanned",IF($K2 < 0.55, "Partially Scanned",IF($K2 >= 0.55, "Fully Scanned","Not Found"))) -> Partially Scanned
A3: 16 | B3: https://modernslaveryregister.gov.au/statements/16/ | C3: =VLOOKUP($A3,Sheet1!$A$2:$I$6793,2,FALSE) -> Normal | D3: =VLOOKUP($A3,Sheet1!$A$2:$I$6793,3,FALSE) -> Australia | F3: Unknown | G3: ORIX AUSTRALIA CORPORATION LIMITED (79 002 992 681) | J3: 11 | K3: 0.18181818 | L3: 147 | M3: =IF($K3 < 0.15, "Not Scanned",IF($K3 < 0.55, "Partially Scanned",IF($K3 >= 0.55, "Fully Scanned","Not Found"))) -> Partially Scanned | N3: 11 | O3: 0.18181818 | P3: 147 | Q3: =IF($K3 < 0.15, "Not Scanned",IF($K3 < 0.55, "Partially Scanned",IF($K3 >= 0.55, "Fully Scanned","Not Found"))) -> Partially Scanned
A4: 20 | B4: https://modernslaveryregister.gov.au/statements/20/ | C4: =VLOOKUP($A4,Sheet1!$A$2:$I$6793,2,FALSE) -> Normal | D4: =VLOOKUP($A4,Sheet1!$A$2:$I$6793,3,FALSE) -> Australia | F4: 500-600M | G4: THE UNIVERSITY OF NEWCASTLE (15 736 576 735) | J4: 16 | K4: 1 | L4: 0 | M4: =IF($K4 < 0.15, "Not Scanned",IF($K4 < 0.55, "Partially Scanned",IF($K4 >= 0.55, "Fully Scanned","Not Found"))) -> Fully Scanned | N4: 16 | O4: 1 | P4: 0 | Q4: =IF($K4 < 0.15, "Not Scanned",IF($K4 < 0.55, "Partially Scanned",IF($K4 >= 0.55, "Fully Scanned","Not Found"))) -> Fully Scanned
A5: 24 | B5: https://modernslaveryregister.gov.au/statements/24/ | C5: =VLOOKUP($A5,Sheet1!$A$2:$I$6793,2,FALSE) -> Joint | D5: =VLOOKUP($A5,Sheet1!$A$2:$I$6793,3,FALSE) -> United States of America | F5: Unknown | G5: Reinsurance Group of America Incorporated, RGA REINSURANCE COMPANY OF AUSTRALIA LIMITED (14 072 292 712), RGA UK Services Limited | J5: 3 | K5: 1 | L5: 0 | M5: =IF($K5 < 0.15, "Not Scanned",IF($K5 < 0.55, "Partially Scanned",IF($K5 >= 0.55, "Fully Scanned","Not Found"))) -> Fully Scanned | N5: 3 | O5: 1 | P5: 0 | Q5: =IF($K5 < 0.15, "Not Scanned",IF($K5 < 0.55, "Partially Scanned",IF($K5 >= 0.55, "Fully Scanned","Not Found"))) -> Fully Scanned
A6: 35 | B6: https://modernslaveryregister.gov.au/statements/35/ | C6: =VLOOKUP($A6,Sheet1!$A$2:$I$6793,2,FALSE) -> Normal | D6: =VLOOKUP($A6,Sheet1!$A$2:$I$6793,3,FALSE) -> Australia | F6: Unknown | G6: ALDI STORES (A LIMITED PARTNERSHIP) (90 196 565 019) | J6: 23 | K6: 0.043478261 | L6: 244 | M6: =IF($K6 < 0.15, "Not Scanned",IF($K6 < 0.55, "Partially Scanned",IF($K6 >= 0.55, "Fully Scanned","Not Found"))) -> Not Scanned | N6: 23 | O6: 0.043478261 | P6: 244 | Q6: =IF($K6 < 0.15, "Not Scanned",IF($K6 < 0.55, "Partially Scanned",IF($K6 >= 0.55, "Fully Scanned","Not Found"))) -> Not Scanned
A7: 37 | B7: https://modernslaveryregister.gov.au/statements/37/ | C7: =VLOOKUP($A7,Sheet1!$A$2:$I$6793,2,FALSE) -> Joint | D7: =VLOOKUP($A7,Sheet1!$A$2:$I$6793,3,FALSE) -> Australia | E7: KPMG Australia | F7: Unknown | G7: KPMG Australia (51 194 660 183), KPMG FINANCIAL ADVISORY SERVICES (AUSTRALIA) PTY LTD (43 007 363 215), KPMG HOLDINGS (AUSTRALIA) PTY LTD (34 064 067 241), The Trustee for KPMG AUSTRALIAN SERVICE TRUST (87 160 010 116) | J7: 22 | K7: 0.045454545 | L7: 397 | M7: =IF($K7 < 0.15, "Not Scanned",IF($K7 < 0.55, "Partially Scanned",IF($K7 >= 0.55, "Fully Scanned","Not Found"))) -> Not Scanned | N7: 22 | O7: 0.045454545 | P7: 397 | Q7: =IF($K7 < 0.15, "Not Scanned",IF($K7 < 0.55, "Partially Scanned",IF($K7 >= 0.55, "Fully Scanned","Not Found"))) -> Not Scanned
A8: 39 | B8: https://modernslaveryregister.gov.au/statements/39/ | C8: =VLOOKUP($A8,Sheet1!$A$2:$I$6793,2,FALSE) -> Joint | D8: =VLOOKUP($A8,Sheet1!$A$2:$I$6793,3,FALSE) -> Australia | E8: Santos | F8: 1BN+ | G8: SANTOS LIMITED (80 007 550 923) | J8: 22 | K8: 0.045454545 | L8: 269 | M8: =IF($K8 < 0.15, "Not Scanned",IF($K8 < 0.55, "Partially Scanned",IF($K8 >= 0.55, "Fully Scanned","Not Found"))) -> Not Scanned | N8: 22 | O8: 0.045454545 | P8: 269 | Q8: =IF($K8 < 0.15, "Not Scanned",IF($K8 < 0.55, "Partially Scanned",IF($K8 >= 0.55, "Fully Scanned","Not Found"))) -> Not Scanned
A9: 40 | B9: https://modernslaveryregister.gov.au/statements/40/ | C9: =VLOOKUP($A9,Sheet1!$A$2:$I$6793,2,FALSE) -> Normal | D9: =VLOOKUP($A9,Sheet1!$A$2:$I$6793,3,FALSE) -> Ireland | E9: Kerry | F9: 200-250M | G9: KERRY INGREDIENTS AUSTRALIA PTY. LIMITED (47 072 996 895) | J9: 3 | K9: 0 | L9: 765 | M9: =IF($K9 < 0.15, "Not Scanned",IF($K9 < 0.55, "Partially Scanned",IF($K9 >= 0.55, "Fully Scanned","Not Found"))) -> Not Scanned | N9: 3 | O9: 0 | P9: 765 | Q9: =IF($K9 < 0.15, "Not Scanned",IF($K9 < 0.55, "Partially Scanned",IF($K9 >= 0.55, "Fully Scanned","Not Found"))) -> Not Scanned
A10: 41 | B10: https://modernslaveryregister.gov.au/statements/41/ | C10: =VLOOKUP($A10,Sheet1!$A$2:$I$6793,2,FALSE) -> Joint | D10: =VLOOKUP($A10,Sheet1!$A$2:$I$6793,3,FALSE) -> United Kingdom | E10: BT | F10: 200-250M | G10: BT AUSTRALASIA PTY LIMITED (93 003 050 146) | J10: 22 | K10: 0.045454545 | L10: 377.5 | M10: =IF($K10 < 0.15, "Not Scanned",IF($K10 < 0.55, "Partially Scanned",IF($K10 >= 0.55, "Fully Scanned","Not Found"))) -> Not Scanned | N10: 22 | O10: 0.045454545 | P10: 377.5 | Q10: =IF($K10 < 0.15, "Not Scanned",IF($K10 < 0.55, "Partially Scanned",IF($K10 >= 0.55, "Fully Scanned","Not Found"))) -> Not Scanned
A11: 49 | B11: https://modernslaveryregister.gov.au/statements/49/ | C11: =VLOOKUP($A11,Sheet1!$A$2:$I$6793,2,FALSE) -> Normal | D11: =VLOOKUP($A11,Sheet1!$A$2:$I$6793,3,FALSE) -> Australia | E11: Bose, Bose Corporation | F11: Unknown | G11: Bose Pty Ltd | H11: Other | I11: United Kingdom Modern Slavery Act 2015 California Transparency in Supply Chains Act 2010 | J11: 3 | K11: 1 | L11: 0 | M11: =IF($K11 < 0.15, "Not Scanned",IF($K11 < 0.55, "Partially Scanned",IF($K11 >= 0.55, "Fully Scanned","Not Found"))) -> Fully Scanned | N11: 3 | O11: 1 | P11: 0 | Q11: =IF($K11 < 0.15, "Not Scanned",IF($K11 < 0.55, "Partially Scanned",IF($K11 >= 0.55, "Fully Scanned","Not Found"))) -> Fully Scanned
A12: 51 | B12: https://modernslaveryregister.gov.au/statements/51/ | C12: =VLOOKUP($A12,Sheet1!$A$2:$I$6793,2,FALSE) -> Joint | D12: =VLOOKUP($A12,Sheet1!$A$2:$I$6793,3,FALSE) -> Australia, New Zealand | E12: Xero, HubDoc, WorkflowMax | F12: 700-800M | G12: XERO AUSTRALIA PTY LIMITED (89 124 215 247), Xero Limited (81 160 661 183) | J12: 8 | K12: 0 | L12: 281.5 | M12: =IF($K12 < 0.15, "Not Scanned",IF($K12 < 0.55, "Partially Scanned",IF($K12 >= 0.55, "Fully Scanned","Not Found"))) -> Not Scanned | N12: 8 | O12: 0 | P12: 281.5 | Q12: =IF($K12 < 0.15, "Not Scanned",IF($K12 < 0.55, "Partially Scanned",IF($K12 >= 0.55, "Fully Scanned","Not Found"))) -> Not Scanned
A13: 58 | B13: https://modernslaveryregister.gov.au/statements/58/ | C13: =VLOOKUP($A13,Sheet1!$A$2:$I$6793,2,FALSE) -> Joint | D13: =VLOOKUP($A13,Sheet1!$A$2:$I$6793,3,FALSE) -> Australia, United Kingdom | E13: Menzies Aviation, AMI, Air Menzies International | F13: 300-350M | G13: John Menzies plc, MENZIES AVIATION (GROUND SERVICES) AUSTRALIA PTY LTD (63 085 693 269), MENZIES AVIATION HOLDINGS (AUSTRALIA) PTY LTD (18 102 031 836) | J13: 8 | K13: 0.625 | L13: 9.5 | M13: =IF($K13 < 0.15, "Not Scanned",IF($K13 < 0.55, "Partially Scanned",IF($K13 >= 0.55, "Fully Scanned","Not Found"))) -> Fully Scanned | N13: 8 | O13: 0.625 | P13: 9.5 | Q13: =IF($K13 < 0.15, "Not Scanned",IF($K13 < 0.55, "Partially Scanned",IF($K13 >= 0.55, "Fully Scanned","Not Found"))) -> Fully Scanned
A14: 61 | B14: https://modernslaveryregister.gov.au/statements/61/ | C14: =VLOOKUP($A14,Sheet1!$A$2:$I$6793,2,FALSE) -> Joint | D14: =VLOOKUP($A14,Sheet1!$A$2:$I$6793,3,FALSE) -> Australia | E14: Baby Bunting | F14: 800-900M | G14: BABY BUNTING GROUP LIMITED (58 128 533 693), BABY BUNTING PTY LTD (43 128 546 154) | H14: Durable consumer goods, including electronics and appliances, home furnishings and other accessories Fashion, textiles, apparel and luxury goods | J14: 3 | K14: 0 | L14: 583 | M14: =IF($K14 < 0.15, "Not Scanned",IF($K14 < 0.55, "Partially Scanned",IF($K14 >= 0.55, "Fully Scanned","Not Found"))) -> Not Scanned | N14: 3 | O14: 0 | P14: 583 | Q14: =IF($K14 < 0.15, "Not Scanned",IF($K14 < 0.55, "Partially Scanned",IF($K14 >= 0.55, "Fully Scanned","Not Found"))) -> Not Scanned
A15: 62 | B15: https://modernslaveryregister.gov.au/statements/62/ | C15: =VLOOKUP($A15,Sheet1!$A$2:$I$6793,2,FALSE) -> Normal | D15: =VLOOKUP($A15,Sheet1!$A$2:$I$6793,3,FALSE) -> Japan | F15: Unknown | G15: OBAYASHI CORPORATION (86 002 932 756) | H15: Construction, civil engineering and building products | I15: United Kingdom Modern Slavery Act 2015 | J15: 8 | K15: 0.125 | L15: 360.5 | M15: =IF($K15 < 0.15, "Not Scanned",IF($K15 < 0.55, "Partially Scanned",IF($K15 >= 0.55, "Fully Scanned","Not Found"))) -> Not Scanned | N15: 8 | O15: 0.125 | P15: 360.5 | Q15: =IF($K15 < 0.15, "Not Scanned",IF($K15 < 0.55, "Partially Scanned",IF($K15 >= 0.55, "Fully Scanned","Not Found"))) -> Not Scanned
A16: 68 | B16: https://modernslaveryregister.gov.au/statements/68/ | C16: =VLOOKUP($A16,Sheet1!$A$2:$I$6793,2,FALSE) -> Joint | D16: =VLOOKUP($A16,Sheet1!$A$2:$I$6793,3,FALSE) -> United States of America | E16: Jamf Holding Corp. | F16: 200-250M | G16: JAMF SOFTWARE AUSTRALIA PTY LTD (47 165 322 154) | J16: 2 | K16: 0 | L16: 346.5 | M16: =IF($K16 < 0.15, "Not Scanned",IF($K16 < 0.55, "Partially Scanned",IF($K16 >= 0.55, "Fully Scanned","Not Found"))) -> Not Scanned | N16: 2 | O16: 0 | P16: 346.5 | Q16: =IF($K16 < 0.15, "Not Scanned",IF($K16 < 0.55, "Partially Scanned",IF($K16 >= 0.55, "Fully Scanned","Not Found"))) -> Not Scanned
A17: 70 | B17: https://modernslaveryregister.gov.au/statements/70/ | C17: =VLOOKUP($A17,Sheet1!$A$2:$I$6793,2,FALSE) -> Joint | D17: =VLOOKUP($A17,Sheet1!$A$2:$I$6793,3,FALSE) -> United States of America | E17: Nielsen, Nielsen IQ, Nielsen Connect, Nielsen TAM, Netratings, Nielsen Sports | F17: 1BN+ | G17: NETRATINGS AUSTRALIA PTY LIMITED (47 081 796 287), NIELSEN CONNECT AUSTRALIA PTY LTD (97 638 234 474), NIELSEN SPORTS PTY LTD (59 106 863 325), NIELSEN TELEVISION AUDIENCE MEASUREMENT PTY LTD (57 089 686 500), THE NIELSEN COMPANY (AUSTRALIA) PTY LTD (35 008 417 874) | J17: 10 | K17: 0.1 | L17: 358.5 | M17: =IF($K17 < 0.15, "Not Scanned",IF($K17 < 0.55, "Partially Scanned",IF($K17 >= 0.55, "Fully Scanned","Not Found"))) -> Not Scanned | N17: 10 | O17: 0.1 | P17: 358.5 | Q17: =IF($K17 < 0.15, "Not Scanned",IF($K17 < 0.55, "Partially Scanned",IF($K17 >= 0.55, "Fully Scanned","Not Found"))) -> Not Scanned
A18: 74 | B18: https://modernslaveryregister.gov.au/statements/74/ | C18: =VLOOKUP($A18,Sheet1!$A$2:$I$6793,2,FALSE) -> Normal | D18: =VLOOKUP($A18,Sheet1!$A$2:$I$6793,3,FALSE) -> Australia | F18: 800-900M | G18: BRADKEN PTY LIMITED (33 108 693 009) | H18: Other | J18: 14 | K18: 0 | L18: 471.5 | M18: =IF($K18 < 0.15, "Not Scanned",IF($K18 < 0.55, "Partially Scanned",IF($K18 >= 0.55, "Fully Scanned","Not Found"))) -> Not Scanned | N18: 14 | O18: 0 | P18: 471.5 | Q18: =IF($K18 < 0.15, "Not Scanned",IF($K18 < 0.55, "Partially Scanned",IF($K18 >= 0.55, "Fully Scanned","Not Found"))) -> Not Scanned
A19: 75 | B19: https://modernslaveryregister.gov.au/statements/75/ | C19: =VLOOKUP($A19,Sheet1!$A$2:$I$6793,2,FALSE) -> Joint | D19: =VLOOKUP($A19,Sheet1!$A$2:$I$6793,3,FALSE) -> Australia, Singapore | E19: Australasian Solvents and Chemical Company, ASCC, Taytonn | F19: 250-300M | G19: AUSTRALASIAN SOLVENTS AND CHEMICALS COMPANY PTY. LTD. (57 095 441 080) | H19: Mining, metals, chemicals and resources (including oil and gas) | J19: 3 | K19: 1 | L19: 0 | M19: =IF($K19 < 0.15, "Not Scanned",IF($K19 < 0.55, "Partially Scanned",IF($K19 >= 0.55, "Fully Scanned","Not Found"))) -> Fully Scanned | N19: 3 | O19: 1 | P19: 0 | Q19: =IF($K19 < 0.15, "Not Scanned",IF($K19 < 0.55, "Partially Scanned",IF($K19 >= 0.55, "Fully Scanned","Not Found"))) -> Fully Scanned
A20: 77 | B20: https://modernslaveryregister.gov.au/statements/77/ | C20: =VLOOKUP($A20,Sheet1!$A$2:$I$6793,2,FALSE) -> Normal | D20: =VLOOKUP($A20,Sheet1!$A$2:$I$6793,3,FALSE) -> Australia | E20: Caroma, Methven, Dorf, Clark | F20: 350-400M | G20: GWA GROUP LIMITED (15 055 964 380) | H20: Construction, civil engineering and building products | J20: 6 | K20: 0 | L20: 375.5 | M20: =IF($K20 < 0.15, "Not Scanned",IF($K20 < 0.55, "Partially Scanned",IF($K20 >= 0.55, "Fully Scanned","Not Found"))) -> Not Scanned | N20: 6 | O20: 0 | P20: 375.5 | Q20: =IF($K20 < 0.15, "Not Scanned",IF($K20 < 0.55, "Partially Scanned",IF($K20 >= 0.55, "Fully Scanned","Not Found"))) -> Not Scanned
A21: 79 | B21: https://modernslaveryregister.gov.au/statements/79/ | C21: =VLOOKUP($A21,Sheet1!$A$2:$I$6793,2,FALSE) -> Normal | D21: =VLOOKUP($A21,Sheet1!$A$2:$I$6793,3,FALSE) -> Australia | E21: NEC | F21: 350-400M | G21: NEC AUSTRALIA PTY LTD (86 001 217 527) | J21: 3 | K21: 0.33333333 | L21: 361 | M21: =IF($K21 < 0.15, "Not Scanned",IF($K21 < 0.55, "Partially Scanned",IF($K21 >= 0.55, "Fully Scanned","Not Found"))) -> Partially Scanned | N21: 3 | O21: 0.33333333 | P21: 361 | Q21: =IF($K21 < 0.15, "Not Scanned",IF($K21 < 0.55, "Partially Scanned",IF($K21 >= 0.55, "Fully Scanned","Not Found"))) -> Partially Scanned
A22: 83 | B22: https://modernslaveryregister.gov.au/statements/83/ | C22: =VLOOKUP($A22,Sheet1!$A$2:$I$6793,2,FALSE) -> Normal | D22: =VLOOKUP($A22,Sheet1!$A$2:$I$6793,3,FALSE) -> Australia | E22: Dexus | F22: 1BN+ | G22: DEXUS FUNDS MANAGEMENT LIMITED (24 060 920 783) | J22: 5 | K22: 0 | L22: 471 | M22: =IF($K22 < 0.15, "Not Scanned",IF($K22 < 0.55, "Partially Scanned",IF($K22 >= 0.55, "Fully Scanned","Not Found"))) -> Not Scanned | N22: 5 | O22: 0 | P22: 471 | Q22: =IF($K22 < 0.15, "Not Scanned",IF($K22 < 0.55, "Partially Scanned",IF($K22 >= 0.55, "Fully Scanned","Not Found"))) -> Not Scanned
A23: 88 | B23: https://modernslaveryregister.gov.au/statements/88/ | C23: =VLOOKUP($A23,Sheet1!$A$2:$I$6793,2,FALSE) -> Normal | D23: =VLOOKUP($A23,Sheet1!$A$2:$I$6793,3,FALSE) -> Australia | F23: 1BN+ | G23: Origin Energy Limited | J23: 14 | K23: 0.071428571 | L23: 369 | M23: =IF($K23 < 0.15, "Not Scanned",IF($K23 < 0.55, "Partially Scanned",IF($K23 >= 0.55, "Fully Scanned","Not Found"))) -> Not Scanned | N23: 14 | O23: 0.071428571 | P23: 369 | Q23: =IF($K23 < 0.15, "Not Scanned",IF($K23 < 0.55, "Partially Scanned",IF($K23 >= 0.55, "Fully Scanned","Not Found"))) -> Not Scanned
A24: 91 | B24: https://modernslaveryregister.gov.au/statements/91/ | C24: =VLOOKUP($A24,Sheet1!$A$2:$I$6793,2,FALSE) -> Normal | D24: =VLOOKUP($A24,Sheet1!$A$2:$I$6793,3,FALSE) -> Australia | E24: M&C Saatchi Melbourne Pty Ltd, M&C Saatchi Sport and Entertainment Pty Ltd, Bohemia Group Pty Ltd, Re Team Australia Pty Ltd, Yes Agency Australia Pty Ltd, Greenhouse Australia Pty Ltd, This Film Studio Pty Ltd, The Source Australia Pty Ltd, Resolution Design Pty Ltd, Elastic Production Pty Ltd, Hidden Characters Pty Ltd, Tricky Jigsaw Pty Ltd, Ugly Sydney pty Ltd, Saatchi Ventures Pty Ltd, House Key Productions Pty Ltd | F24: Unknown | G24: M & C SAATCHI AGENCY PTY LIMITED (30 069 431 054) | J24: 2 | K24: 1 | L24: 0 | M24: =IF($K24 < 0.15, "Not Scanned",IF($K24 < 0.55, "Partially Scanned",IF($K24 >= 0.55, "Fully Scanned","Not Found"))) -> Fully Scanned | N24: 2 | O24: 1 | P24: 0 | Q24: =IF($K24 < 0.15, "Not Scanned",IF($K24 < 0.55, "Partially Scanned",IF($K24 >= 0.55, "Fully Scanned","Not Found"))) -> Fully Scanned
A25: 95 | B25: https://modernslaveryregister.gov.au/statements/95/ | C25: =VLOOKUP($A25,Sheet1!$A$2:$I$6793,2,FALSE) -> Joint | D25: =VLOOKUP($A25,Sheet1!$A$2:$I$6793,3,FALSE) -> Australia | E25: ASX, ASX24, Austraclear, ASX Clear, ASX Clear (Futures) | F25: 1BN+ | G25: ASX CLEAR (FUTURES) PTY LIMITED (91 050 615 864), ASX CLEARING CORPORATION PTY LIMITED (45 087 801 554), ASX LIMITED (98 008 624 691), ASX OPERATIONS PTY. LTD. (42 004 523 782) | J25: 10 | K25: 0.1 | L25: 317 | M25: =IF($K25 < 0.15, "Not Scanned",IF($K25 < 0.55, "Partially Scanned",IF($K25 >= 0.55, "Fully Scanned","Not Found"))) -> Not Scanned | N25: 10 | O25: 0.1 | P25: 317 | Q25: =IF($K25 < 0.15, "Not Scanned",IF($K25 < 0.55, "Partially Scanned",IF($K25 >= 0.55, "Fully Scanned","Not Found"))) -> Not Scanned
A26: 96 | B26: https://modernslaveryregister.gov.au/statements/96/ | C26: =VLOOKUP($A26,Sheet1!$A$2:$I$6793,2,FALSE) -> Joint | D26: =VLOOKUP($A26,Sheet1!$A$2:$I$6793,3,FALSE) -> United States of America | E26: Intel, McAfee | F26: 150-200M | G26: Intel Australia Pty, Limited, McAfee Australia Pty, Limited | J26: 8 | K26: 0.125 | L26: 559.5 | M26: =IF($K26 < 0.15, "Not Scanned",IF($K26 < 0.55, "Partially Scanned",IF($K26 >= 0.55, "Fully Scanned","Not Found"))) -> Not Scanned | N26: 8 | O26: 0.125 | P26: 559.5 | Q26: =IF($K26 < 0.15, "Not Scanned",IF($K26 < 0.55, "Partially Scanned",IF($K26 >= 0.55, "Fully Scanned","Not Found"))) -> Not Scanned
A27: 97 | B27: https://modernslaveryregister.gov.au/statements/97/ | C27: =VLOOKUP($A27,Sheet1!$A$2:$I$6793,2,FALSE) -> Joint | D27: =VLOOKUP($A27,Sheet1!$A$2:$I$6793,3,FALSE) -> Australia | E27: Nando's | F27: Unknown | G27: NANDO'S AUSTRALIA PTY LTD (20 079 066 407), NANDO'S PERI-PERI AUSTRALIA PTY LTD (86 627 885 956) | J27: 10 | K27: 0 | L27: 530 | M27: =IF($K27 < 0.15, "Not Scanned",IF($K27 < 0.55, "Partially Scanned",IF($K27 >= 0.55, "Fully Scanned","Not Found"))) -> Not Scanned | N27: 10 | O27: 0 | P27: 530 | Q27: =IF($K27 < 0.15, "Not Scanned",IF($K27 < 0.55, "Partially Scanned",IF($K27 >= 0.55, "Fully Scanned","Not Found"))) -> Not Scanned
A28: 103 | B28: https://modernslaveryregister.gov.au/statements/103/ | C28: =VLOOKUP($A28,Sheet1!$A$2:$I$6793,2,FALSE) -> Normal | D28: =VLOOKUP($A28,Sheet1!$A$2:$I$6793,3,FALSE) -> Australia | E28: Stockland | F28: 1BN+ | G28: STOCKLAND CORPORATION LTD (43 000 181 733) | J28: 8 | K28: 0 | L28: 432 | M28: =IF($K28 < 0.15, "Not Scanned",IF($K28 < 0.55, "Partially Scanned",IF($K28 >= 0.55, "Fully Scanned","Not Found"))) -> Not Scanned | N28: 8 | O28: 0 | P28: 432 | Q28: =IF($K28 < 0.15, "Not Scanned",IF($K28 < 0.55, "Partially Scanned",IF($K28 >= 0.55, "Fully Scanned","Not Found"))) -> Not Scanned
A29: 106 | B29: https://modernslaveryregister.gov.au/statements/106/ | C29: =VLOOKUP($A29,Sheet1!$A$2:$I$6793,2,FALSE) -> Normal | D29: =VLOOKUP($A29,Sheet1!$A$2:$I$6793,3,FALSE) -> Australia | E29: Allhomes, Australian Property Monitors, Commercial Real Estate, Domain, Domain Insure, Domain Loan Finder, Domain Review, Homepass, Pricefinder | F29: 250-300M | G29: DOMAIN HOLDINGS AUSTRALIA LIMITED (43 094 154 364) | J29: 4 | K29: 0.25 | L29: 442 | M29: =IF($K29 < 0.15, "Not Scanned",IF($K29 < 0.55, "Partially Scanned",IF($K29 >= 0.55, "Fully Scanned","Not Found"))) -> Partially Scanned | N29: 4 | O29: 0.25 | P29: 442 | Q29: =IF($K29 < 0.15, "Not Scanned",IF($K29 < 0.55, "Partially Scanned",IF($K29 >= 0.55, "Fully Scanned","Not Found"))) -> Partially Scanned
A30: 113 | B30: https://modernslaveryregister.gov.au/statements/113/ | C30: =VLOOKUP($A30,Sheet1!$A$2:$I$6793,2,FALSE) -> Normal | D30: =VLOOKUP($A30,Sheet1!$A$2:$I$6793,3,FALSE) -> Czech Republic, United Kingdom | E30: Avast plc, Avast Software s.r.o., AVG Technologies | F30: 800-900M | G30: AVG TECHNOLOGIES AU PTY LTD (79 159 743 978) | J30: 6 | K30: 0 | L30: 339.5 | M30: =IF($K30 < 0.15, "Not Scanned",IF($K30 < 0.55, "Partially Scanned",IF($K30 >= 0.55, "Fully Scanned","Not Found"))) -> Not Scanned | N30: 6 | O30: 0 | P30: 339.5 | Q30: =IF($K30 < 0.15, "Not Scanned",IF($K30 < 0.55, "Partially Scanned",IF($K30 >= 0.55, "Fully Scanned","Not Found"))) -> Not Scanned
A31: 115 | B31: https://modernslaveryregister.gov.au/statements/115/ | C31: =VLOOKUP($A31,Sheet1!$A$2:$I$6793,2,FALSE) -> Normal | D31: =VLOOKUP($A31,Sheet1!$A$2:$I$6793,3,FALSE) -> Australia | E31: Ethical Merch Co | F31: 0-99M | G31: CONCIERGE CONTACTS PTY. LTD. (53 149 081 756) | J31: 20 | K31: 0.2 | L31: 143.5 | M31: =IF($K31 < 0.15, "Not Scanned",IF($K31 < 0.55, "Partially Scanned",IF($K31 >= 0.55, "Fully Scanned","Not Found"))) -> Partially Scanned | N31: 20 | O31: 0.2 | P31: 143.5 | Q31: =IF($K31 < 0.15, "Not Scanned",IF($K31 < 0.55, "Partially Scanned",IF($K31 >= 0.55, "Fully Scanned","Not Found"))) -> Partially Scanned
A32: 120 | B32: https://modernslaveryregister.gov.au/statements/120/ | C32: =VLOOKUP($A32,Sheet1!$A$2:$I$6793,2,FALSE) -> Joint | D32: =VLOOKUP($A32,Sheet1!$A$2:$I$6793,3,FALSE) -> Australia | E32: Betta Home Living, Designer Appliances, Furniture Zone, Norj, Betta, Torino | F32: 100-150M | G32: BSR Australia Limited (84 122 529 695), BSR Franchising Pty Ltd (21 122 556 094) | J32: 2 | K32: 0 | L32: 434 | M32: =IF($K32 < 0.15, "Not Scanned",IF($K32 < 0.55, "Partially Scanned",IF($K32 >= 0.55, "Fully Scanned","Not Found"))) -> Not Scanned | N32: 2 | O32: 0 | P32: 434 | Q32: =IF($K32 < 0.15, "Not Scanned",IF($K32 < 0.55, "Partially Scanned",IF($K32 >= 0.55, "Fully Scanned","Not Found"))) -> Not Scanned
A33: 123 | B33: https://modernslaveryregister.gov.au/statements/123/ | C33: =VLOOKUP($A33,Sheet1!$A$2:$I$6793,2,FALSE) -> Normal | D33: =VLOOKUP($A33,Sheet1!$A$2:$I$6793,3,FALSE) -> Japan | F33: Unknown | G33: MITSUBISHI AUSTRALIA LIMITED (81 004 354 278) | J33: 3 | K33: 0 | L33: 343 | M33: =IF($K33 < 0.15, "Not Scanned",IF($K33 < 0.55, "Partially Scanned",IF($K33 >= 0.55, "Fully Scanned","Not Found"))) -> Not Scanned | N33: 3 | O33: 0 | P33: 343 | Q33: =IF($K33 < 0.15, "Not Scanned",IF($K33 < 0.55, "Partially Scanned",IF($K33 >= 0.55, "Fully Scanned","Not Found"))) -> Not Scanned
A34: 126 | B34: https://modernslaveryregister.gov.au/statements/126/ | C34: =VLOOKUP($A34,Sheet1!$A$2:$I$6793,2,FALSE) -> Joint | D34: =VLOOKUP($A34,Sheet1!$A$2:$I$6793,3,FALSE) -> Australia | E34: Saracen | F34: 1BN+ | G34: BLIGH RESOURCES LIMITED (83 130 964 162), KALGOORLIE CONSOLIDATED GOLD MINES PTY LTD (97 009 377 619), SARACEN GOLDFIELDS PTY LTD (44 637 156 579), SARACEN GOLD MINES PTY LIMITED (14 116 649 122), SARACEN KALGOORLIE PTY LIMITED (19 008 143 137), SARACEN METALS PTY LIMITED (15 107 154 727), SARACEN MINERAL HOLDINGS LIMITED (52 009 215 347), SARACEN NICKEL PTY LTD (57 635 649 606), S R Mining Pty Ltd (91 151 605 417), TALISMAN NICKEL PTY LTD (42 601 140 185) | J34: 5 | K34: 0.2 | L34: 386 | M34: =IF($K34 < 0.15, "Not Scanned",IF($K34 < 0.55, "Partially Scanned",IF($K34 >= 0.55, "Fully Scanned","Not Found"))) -> Partially Scanned | N34: 5 | O34: 0.2 | P34: 386 | Q34: =IF($K34 < 0.15, "Not Scanned",IF($K34 < 0.55, "Partially Scanned",IF($K34 >= 0.55, "Fully Scanned","Not Found"))) -> Partially Scanned
A35: 132 | B35: https://modernslaveryregister.gov.au/statements/132/ | C35: =VLOOKUP($A35,Sheet1!$A$2:$I$6793,2,FALSE) -> Normal | D35: =VLOOKUP($A35,Sheet1!$A$2:$I$6793,3,FALSE) -> Australia | E35: Knights Rugby League, The Executive Inn, The Wests Group Australia, Wests | F35: 150-200M | G35: WESTERN SUBURBS (N'CLE) LEAGUES CLUB LTD (24 000 973 919) | J35: 4 | K35: 1 | L35: 0 | M35: =IF($K35 < 0.15, "Not Scanned",IF($K35 < 0.55, "Partially Scanned",IF($K35 >= 0.55, "Fully Scanned","Not Found"))) -> Fully Scanned | N35: 4 | O35: 1 | P35: 0 | Q35: =IF($K35 < 0.15, "Not Scanned",IF($K35 < 0.55, "Partially Scanned",IF($K35 >= 0.55, "Fully Scanned","Not Found"))) -> Fully Scanned
A36: 134 | B36: https://modernslaveryregister.gov.au/statements/134/ | C36: =VLOOKUP($A36,Sheet1!$A$2:$I$6793,2,FALSE) -> Joint | D36: =VLOOKUP($A36,Sheet1!$A$2:$I$6793,3,FALSE) -> Australia | E36: SOUTH32 | F36: 1BN+ | G36: DENDROBIUM COAL PTY LTD (85 098 744 088), ENDEAVOUR COAL PTY LIMITED (38 099 830 476), GROOTE EYLANDT MINING COMPANY PROPRIETARY LIMITED (26 004 618 491), ILLAWARRA COAL HOLDINGS PTY LTD (69 093 857 286), SOUTH32 ALUMINIUM (RAA) PTY LTD (54 095 831 119), SOUTH32 ALUMINIUM (WORSLEY) PTY LTD (33 088 336 921), SOUTH32 CANNINGTON PROPRIETARY LIMITED (48 125 530 967), SOUTH32 LIMITED (84 093 732 597), TASMANIAN ELECTRO METALLURGICAL COMPANY PROPRIETARY LIMITED (23 004 456 035) | J36: 20 | K36: 0.1 | L36: 389.5 | M36: =IF($K36 < 0.15, "Not Scanned",IF($K36 < 0.55, "Partially Scanned",IF($K36 >= 0.55, "Fully Scanned","Not Found"))) -> Not Scanned | N36: 20 | O36: 0.1 | P36: 389.5 | Q36: =IF($K36 < 0.15, "Not Scanned",IF($K36 < 0.55, "Partially Scanned",IF($K36 >= 0.55, "Fully Scanned","Not Found"))) -> Not Scanned
A37: 136 | B37: https://modernslaveryregister.gov.au/statements/136/ | C37: =VLOOKUP($A37,Sheet1!$A$2:$I$6793,2,FALSE) -> Joint | D37: =VLOOKUP($A37,Sheet1!$A$2:$I$6793,3,FALSE) -> Australia | E37: Autosports Group Limited | F37: 1BN+ | G37: A.C.N. 633 925 050 PTY LTD (59 633 925 050), ASG BRISBANE PTY LTD (72 614 297 684), ASG MELBOURNE PTY LTD (64 616 840 110), AUTOSPORTS BRISBANE PTY LTD (13 603 332 752), AUTOSPORTS CASTLE HILL PTY LTD (65 163 974 481), AUTOSPORTS FIVE DOCK PTY LIMITED (95 118 786 762), AUTOSPORTS GROUP LIMITED (54 614 505 261), AUTOSPORTS LEICHHARDT PTY LTD (38 161 160 765), AUTOSPORTS PRESTIGE PTY LIMITED (42 096 909 698), Autosports Sutherland Pty Limited (60 125 720 998), Betar Prestige Cars Pty Ltd (60 118 667 913), BIRCHGROVE FINANCE PTY LIMITED (90 165 682 057), Modena Trading Pty Ltd (27 140 018 015), Mosman Prestige Cars Pty Ltd (16 149 346 476), NEW CENTENARY MAZDA PTY LTD (21 168 183 800), NEW CENTENARY PTY LIMITED (21 168 183 864), PRESTIGE AUTO TRADERS AUSTRALIA PTY LIMITED (11 105 105 771), PRESTIGE GROUP HOLDINGS PTY LTD (71 073 650 512), PRESTIGE REPAIR WORKS PTY LTD (44 611 760 126) | J37: 5 | K37: 0.2 | L37: 186 | M37: =IF($K37 < 0.15, "Not Scanned",IF($K37 < 0.55, "Partially Scanned",IF($K37 >= 0.55, "Fully Scanned","Not Found"))) -> Partially Scanned | N37: 5 | O37: 0.2 | P37: 186 | Q37: =IF($K37 < 0.15, "Not Scanned",IF($K37 < 0.55, "Partially Scanned",IF($K37 >= 0.55, "Fully Scanned","Not Found"))) -> Partially Scanned
A38: 139 | B38: https://modernslaveryregister.gov.au/statements/139/ | C38: =VLOOKUP($A38,Sheet1!$A$2:$I$6793,2,FALSE) -> Normal | D38: =VLOOKUP($A38,Sheet1!$A$2:$I$6793,3,FALSE) -> Australia | E38: QV, Aqium, SUNSENSE, MOOV, DermAid, Egoderm, Egozite, Elucent, Pinetarsol, Resolve, Sebitar, SolvEasy, SOOV | F38: 150-200M | G38: EGO PHARMACEUTICALS PTY LTD (86 005 142 361) | J38: 7 | K38: 0.14285714 | L38: 343 | M38: =IF($K38 < 0.15, "Not Scanned",IF($K38 < 0.55, "Partially Scanned",IF($K38 >= 0.55, "Fully Scanned","Not Found"))) -> Not Scanned | N38: 7 | O38: 0.14285714 | P38: 343 | Q38: =IF($K38 < 0.15, "Not Scanned",IF($K38 < 0.55, "Partially Scanned",IF($K38 >= 0.55, "Fully Scanned","Not Found"))) -> Not Scanned
A39: 142 | B39: https://modernslaveryregister.gov.au/statements/142/ | C39: =VLOOKUP($A39,Sheet1!$A$2:$I$6793,2,FALSE) -> Normal | D39: =VLOOKUP($A39,Sheet1!$A$2:$I$6793,3,FALSE) -> Australia | E39: GHD | F39: 1BN+ | G39: GHD PTY LTD (39 008 488 373) | J39: 6 | K39: 0 | L39: 326 | M39: =IF($K39 < 0.15, "Not Scanned",IF($K39 < 0.55, "Partially Scanned",IF($K39 >= 0.55, "Fully Scanned","Not Found"))) -> Not Scanned | N39: 6 | O39: 0 | P39: 326 | Q39: =IF($K39 < 0.15, "Not Scanned",IF($K39 < 0.55, "Partially Scanned",IF($K39 >= 0.55, "Fully Scanned","Not Found"))) -> Not Scanned
A40: 144 | B40: https://modernslaveryregister.gov.au/statements/144/ | C40: =VLOOKUP($A40,Sheet1!$A$2:$I$6793,2,FALSE) -> Joint | D40: =VLOOKUP($A40,Sheet1!$A$2:$I$6793,3,FALSE) -> Australia | E40: Channel Nine, Sydney Morning Herald, Stan, The Age, The Australian Financial Review, 9Now | F40: 1BN+ | G40: NINE ENTERTAINMENT CO. HOLDINGS LIMITED (60 122 203 892) | J40: 3 | K40: 0 | L40: 534 | M40: =IF($K40 < 0.15, "Not Scanned",IF($K40 < 0.55, "Partially Scanned",IF($K40 >= 0.55, "Fully Scanned","Not Found"))) -> Not Scanned | N40: 3 | O40: 0 | P40: 534 | Q40: =IF($K40 < 0.15, "Not Scanned",IF($K40 < 0.55, "Partially Scanned",IF($K40 >= 0.55, "Fully Scanned","Not Found"))) -> Not Scanned
A41: 145 | B41: https://modernslaveryregister.gov.au/statements/145/ | C41: =VLOOKUP($A41,Sheet1!$A$2:$I$6793,2,FALSE) -> Normal | D41: =VLOOKUP($A41,Sheet1!$A$2:$I$6793,3,FALSE) -> Australia | E41: HammondCare Health and Hospitals, Dementia Centre, HammondCare At Home | F41: 300-350M | G41: HAMMONDCARE (48 000 026 219) | J41: 17 | K41: 0.23529412 | L41: 182 | M41: =IF($K41 < 0.15, "Not Scanned",IF($K41 < 0.55, "Partially Scanned",IF($K41 >= 0.55, "Fully Scanned","Not Found"))) -> Partially Scanned | N41: 17 | O41: 0.23529412 | P41: 182 | Q41: =IF($K41 < 0.15, "Not Scanned",IF($K41 < 0.55, "Partially Scanned",IF($K41 >= 0.55, "Fully Scanned","Not Found"))) -> Partially Scanned
A42: 154 | B42: https://modernslaveryregister.gov.au/statements/154/ | C42: =VLOOKUP($A42,Sheet1!$A$2:$I$6793,2,FALSE) -> Joint | D42: =VLOOKUP($A42,Sheet1!$A$2:$I$6793,3,FALSE) -> Australia | E42: Woolworths Supermarkets, BIG W, BWS, Dan Murphy's, Countdown, WooliesX, Cellarmasters, Jimmy Brings, Shorty's Liquor, Metro | F42: 1BN+ | G42: ENDEAVOUR GROUP LIMITED (77 159 767 843), WOOLWORTHS GROUP LIMITED (88 000 014 675) | J42: 32 | K42: 0.03125 | L42: 401.5 | M42: =IF($K42 < 0.15, "Not Scanned",IF($K42 < 0.55, "Partially Scanned",IF($K42 >= 0.55, "Fully Scanned","Not Found"))) -> Not Scanned | N42: 32 | O42: 0.03125 | P42: 401.5 | Q42: =IF($K42 < 0.15, "Not Scanned",IF($K42 < 0.55, "Partially Scanned",IF($K42 >= 0.55, "Fully Scanned","Not Found"))) -> Not Scanned
A43: 156 | B43: https://modernslaveryregister.gov.au/statements/156/ | C43: =VLOOKUP($A43,Sheet1!$A$2:$I$6793,2,FALSE) -> Joint | D43: =VLOOKUP($A43,Sheet1!$A$2:$I$6793,3,FALSE) -> Australia | F43: 1BN+ | G43: BHP GROUP LIMITED (49 004 028 077) | J43: 18 | K43: 0.11111111 | L43: 609 | M43: =IF($K43 < 0.15, "Not Scanned",IF($K43 < 0.55, "Partially Scanned",IF($K43 >= 0.55, "Fully Scanned","Not Found"))) -> Not Scanned | N43: 18 | O43: 0.11111111 | P43: 609 | Q43: =IF($K43 < 0.15, "Not Scanned",IF($K43 < 0.55, "Partially Scanned",IF($K43 >= 0.55, "Fully Scanned","Not Found"))) -> Not Scanned
A44: 161 | B44: https://modernslaveryregister.gov.au/statements/161/ | C44: =VLOOKUP($A44,Sheet1!$A$2:$I$6793,2,FALSE) -> Normal | D44: =VLOOKUP($A44,Sheet1!$A$2:$I$6793,3,FALSE) -> Australia | E44: ZINCALUME steel, COLORBOND steel TRUECORE steel | F44: 1BN+ | G44: BLUESCOPE STEEL LIMITED (16 000 011 058) | H44: Construction, civil engineering and building products | I44: California Transparency in Supply Chains Act 2010 | J44: 20 | K44: 0.2 | L44: 345 | M44: =IF($K44 < 0.15, "Not Scanned",IF($K44 < 0.55, "Partially Scanned",IF($K44 >= 0.55, "Fully Scanned","Not Found"))) -> Partially Scanned | N44: 20 | O44: 0.2 | P44: 345 | Q44: =IF($K44 < 0.15, "Not Scanned",IF($K44 < 0.55, "Partially Scanned",IF($K44 >= 0.55, "Fully Scanned","Not Found"))) -> Partially Scanned
A45: 163 | B45: https://modernslaveryregister.gov.au/statements/163/ | C45: =VLOOKUP($A45,Sheet1!$A$2:$I$6793,2,FALSE) -> Joint | D45: =VLOOKUP($A45,Sheet1!$A$2:$I$6793,3,FALSE) -> Japan | F45: 1BN+ | G45: ANRITSU CORPORATION | H45: Information technology and telecommunication | I45: United Kingdom Modern Slavery Act 2015 California Transparency in Supply Chains Act 2010 | J45: 6 | K45: 0 | L45: 295 | M45: =IF($K45 < 0.15, "Not Scanned",IF($K45 < 0.55, "Partially Scanned",IF($K45 >= 0.55, "Fully Scanned","Not Found"))) -> Not Scanned | N45: 6 | O45: 0 | P45: 295 | Q45: =IF($K45 < 0.15, "Not Scanned",IF($K45 < 0.55, "Partially Scanned",IF($K45 >= 0.55, "Fully Scanned","Not Found"))) -> Not Scanned
A46: 165 | B46: https://modernslaveryregister.gov.au/statements/165/ | C46: =VLOOKUP($A46,Sheet1!$A$2:$I$6793,2,FALSE) -> Normal | D46: =VLOOKUP($A46,Sheet1!$A$2:$I$6793,3,FALSE) -> Australia | E46: Atlas Steels, Austral Wright, Dalsteel, Australian Stainless Distributors | F46: 250-300M | G46: Amari Metals Australia Pty Ltd (13 004 486 128) | J46: 3 | K46: 1 | L46: 0 | M46: =IF($K46 < 0.15, "Not Scanned",IF($K46 < 0.55, "Partially Scanned",IF($K46 >= 0.55, "Fully Scanned","Not Found"))) -> Fully Scanned | N46: 3 | O46: 1 | P46: 0 | Q46: =IF($K46 < 0.15, "Not Scanned",IF($K46 < 0.55, "Partially Scanned",IF($K46 >= 0.55, "Fully Scanned","Not Found"))) -> Fully Scanned
A47: 168 | B47: https://modernslaveryregister.gov.au/statements/168/ | C47: =VLOOKUP($A47,Sheet1!$A$2:$I$6793,2,FALSE) -> Joint | D47: =VLOOKUP($A47,Sheet1!$A$2:$I$6793,3,FALSE) -> Australia | E47: CSR, Gyprock, Bradford, PGH, Monier, Hebel, Cemintel, Himmel, AFS, Potter Interior Systems, Martini, Gove Aluminium | F47: 1BN+ | G47: CSR BUILDING PRODUCTS LIMITED (55 008 631 356), CSR LIMITED (90 000 001 276), GOVE ALUMINIUM FINANCE LTD (45 001 860 073), PGH BRICKS & PAVERS PTY LIMITED (68 168 794 821) | J47: 15 | K47: 0.066666667 | L47: 390 | M47: =IF($K47 < 0.15, "Not Scanned",IF($K47 < 0.55, "Partially Scanned",IF($K47 >= 0.55, "Fully Scanned","Not Found"))) -> Not Scanned | N47: 15 | O47: 0.066666667 | P47: 390 | Q47: =IF($K47 < 0.15, "Not Scanned",IF($K47 < 0.55, "Partially Scanned",IF($K47 >= 0.55, "Fully Scanned","Not Found"))) -> Not Scanned
A48: 169 | B48: https://modernslaveryregister.gov.au/statements/169/ | C48: =VLOOKUP($A48,Sheet1!$A$2:$I$6793,2,FALSE) -> Normal | D48: =VLOOKUP($A48,Sheet1!$A$2:$I$6793,3,FALSE) -> Australia | E48: Bidim, Elcoseal, Geofabrics Australasia | F48: 100-150M | G48: GEOFABRICS AUSTRALASIA PTY. LTD. (23 005 479 961) | J48: 2 | K48: 0 | L48: 282.5 | M48: =IF($K48 < 0.15, "Not Scanned",IF($K48 < 0.55, "Partially Scanned",IF($K48 >= 0.55, "Fully Scanned","Not Found"))) -> Not Scanned | N48: 2 | O48: 0 | P48: 282.5 | Q48: =IF($K48 < 0.15, "Not Scanned",IF($K48 < 0.55, "Partially Scanned",IF($K48 >= 0.55, "Fully Scanned","Not Found"))) -> Not Scanned
A49: 172 | B49: https://modernslaveryregister.gov.au/statements/172/ | C49: =VLOOKUP($A49,Sheet1!$A$2:$I$6793,2,FALSE) -> Normal | D49: =VLOOKUP($A49,Sheet1!$A$2:$I$6793,3,FALSE) -> Australia | F49: 100-150M | G49: ASTELLAS PHARMA AUSTRALIA PTY LTD (81 147 915 482) | J49: 5 | K49: 0 | L49: 428 | M49: =IF($K49 < 0.15, "Not Scanned",IF($K49 < 0.55, "Partially Scanned",IF($K49 >= 0.55, "Fully Scanned","Not Found"))) -> Not Scanned | N49: 5 | O49: 0 | P49: 428 | Q49: =IF($K49 < 0.15, "Not Scanned",IF($K49 < 0.55, "Partially Scanned",IF($K49 >= 0.55, "Fully Scanned","Not Found"))) -> Not Scanned
A50: 173 | B50: https://modernslaveryregister.gov.au/statements/173/ | C50: =VLOOKUP($A50,Sheet1!$A$2:$I$6793,2,FALSE) -> Normal | D50: =VLOOKUP($A50,Sheet1!$A$2:$I$6793,3,FALSE) -> United States of America | F50: 900M-1BN | G50: American Airlines, Inc. | J50: 4 | K50: 1 | L50: 0 | M50: =IF($K50 < 0.15, "Not Scanned",IF($K50 < 0.55, "Partially Scanned",IF($K50 >= 0.55, "Fully Scanned","Not Found"))) -> Fully Scanned | N50: 4 | O50: 1 | P50: 0 | Q50: =IF($K50 < 0.15, "Not Scanned",IF($K50 < 0.55, "Partially Scanned",IF($K50 >= 0.55, "Fully Scanned","Not Found"))) -> Fully Scanned
A51: 179 | B51: https://modernslaveryregister.gov.au/statements/179/ | C51: =VLOOKUP($A51,Sheet1!$A$2:$I$6793,2,FALSE) -> Joint | D51: =VLOOKUP($A51,Sheet1!$A$2:$I$6793,3,FALSE) -> Australia | E51: Bunnings, Kmart, Target, Catch, Officeworks, Wesfarmers Chemical Energy and Fertilisers, Blackwoods, Workwear Group, Greencap | F51: 1BN+ | G51: BUNNINGS GROUP LIMITED (26 008 672 179), KMART AUSTRALIA LIMITED (73 004 700 485), OFFICEWORKS LTD (36 004 763 526), WESFARMERS CHEMICALS, ENERGY & FERTILISERS LIMITED (48 008 797 402), Wesfarmers Industrial and Safety Pty Ltd (15 137 253 528) | J51: 16 | K51: 0.125 | L51: 431.5 | M51: =IF($K51 < 0.15, "Not Scanned",IF($K51 < 0.55, "Partially Scanned",IF($K51 >= 0.55, "Fully Scanned","Not Found"))) -> Not Scanned | N51: 16 | O51: 0.125 | P51: 431.5 | Q51: =IF($K51 < 0.15, "Not Scanned",IF($K51 < 0.55, "Partially Scanned",IF($K51 >= 0.55, "Fully Scanned","Not Found"))) -> Not Scanned
A52: 181 | B52: https://modernslaveryregister.gov.au/statements/181/ | C52: =VLOOKUP($A52,Sheet1!$A$2:$I$6793,2,FALSE) -> Joint | D52: =VLOOKUP($A52,Sheet1!$A$2:$I$6793,3,FALSE) -> Australia | F52: 1BN+ | G52: GOODMAN FUNDS MANAGEMENT LIMITED (48 067 796 641), GOODMAN LIMITED (69 000 123 071), Goodman Logistics (HK) Limited | J52: 7 | K52: 0 | L52: 396 | M52: =IF($K52 < 0.15, "Not Scanned",IF($K52 < 0.55, "Partially Scanned",IF($K52 >= 0.55, "Fully Scanned","Not Found"))) -> Not Scanned | N52: 7 | O52: 0 | P52: 396 | Q52: =IF($K52 < 0.15, "Not Scanned",IF($K52 < 0.55, "Partially Scanned",IF($K52 >= 0.55, "Fully Scanned","Not Found"))) -> Not Scanned
A53: 185 | B53: https://modernslaveryregister.gov.au/statements/185/ | C53: =VLOOKUP($A53,Sheet1!$A$2:$I$6793,2,FALSE) -> Normal | D53: =VLOOKUP($A53,Sheet1!$A$2:$I$6793,3,FALSE) -> Australia | E53: Clifford Hallam Healthcare, CH2, Bare Medical | F53: 1BN+ | G53: CLIFFORD HALLAM HEALTHCARE PTY LIMITED (38 001 655 554) | J53: 3 | K53: 1 | L53: 0 | M53: =IF($K53 < 0.15, "Not Scanned",IF($K53 < 0.55, "Partially Scanned",IF($K53 >= 0.55, "Fully Scanned","Not Found"))) -> Fully Scanned | N53: 3 | O53: 1 | P53: 0 | Q53: =IF($K53 < 0.15, "Not Scanned",IF($K53 < 0.55, "Partially Scanned",IF($K53 >= 0.55, "Fully Scanned","Not Found"))) -> Fully Scanned
A54: 193 | B54: https://modernslaveryregister.gov.au/statements/193/ | C54: =VLOOKUP($A54,Sheet1!$A$2:$I$6793,2,FALSE) -> Joint | D54: =VLOOKUP($A54,Sheet1!$A$2:$I$6793,3,FALSE) -> Australia | F54: 400-450M | G54: AUSENCO LIMITED (31 114 541 114) | J54: 7 | K54: 0 | L54: 377 | M54: =IF($K54 < 0.15, "Not Scanned",IF($K54 < 0.55, "Partially Scanned",IF($K54 >= 0.55, "Fully Scanned","Not Found"))) -> Not Scanned | N54: 7 | O54: 0 | P54: 377 | Q54: =IF($K54 < 0.15, "Not Scanned",IF($K54 < 0.55, "Partially Scanned",IF($K54 >= 0.55, "Fully Scanned","Not Found"))) -> Not Scanned
A55: 205 | B55: https://modernslaveryregister.gov.au/statements/205/ | C55: =VLOOKUP($A55,Sheet1!$A$2:$I$6793,2,FALSE) -> Normal | D55: =VLOOKUP($A55,Sheet1!$A$2:$I$6793,3,FALSE) -> Australia | F55: 250-300M | G55: KONICA MINOLTA BUSINESS SOLUTIONS AUSTRALIA PTY LTD (50 001 065 096) | J55: 19 | K55: 0 | L55: 453 | M55: =IF($K55 < 0.15, "Not Scanned",IF($K55 < 0.55, "Partially Scanned",IF($K55 >= 0.55, "Fully Scanned","Not Found"))) -> Not Scanned | N55: 19 | O55: 0 | P55: 453 | Q55: =IF($K55 < 0.15, "Not Scanned",IF($K55 < 0.55, "Partially Scanned",IF($K55 >= 0.55, "Fully Scanned","Not Found"))) -> Not Scanned
A56: 206 | B56: https://modernslaveryregister.gov.au/statements/206/ | C56: =VLOOKUP($A56,Sheet1!$A$2:$I$6793,2,FALSE) -> Normal | D56: =VLOOKUP($A56,Sheet1!$A$2:$I$6793,3,FALSE) -> Japan | E56: NEC Corporation | F56: 1BN+ | G56: NEC Corporation | J56: 7 | K56: 1 | L56: 0 | M56: =IF($K56 < 0.15, "Not Scanned",IF($K56 < 0.55, "Partially Scanned",IF($K56 >= 0.55, "Fully Scanned","Not Found"))) -> Fully Scanned | N56: 7 | O56: 1 | P56: 0 | Q56: =IF($K56 < 0.15, "Not Scanned",IF($K56 < 0.55, "Partially Scanned",IF($K56 >= 0.55, "Fully Scanned","Not Found"))) -> Fully Scanned
A57: 212 | B57: https://modernslaveryregister.gov.au/statements/212/ | C57: =VLOOKUP($A57,Sheet1!$A$2:$I$6793,2,FALSE) -> Joint | D57: =VLOOKUP($A57,Sheet1!$A$2:$I$6793,3,FALSE) -> Australia | E57: Coles Supermarkets, Coles Local, First Choice Liquor Market, Vintage Cellars, Liquorland, Coles Express | F57: 1BN+ | G57: COLES GROUP LIMITED (11 004 089 936) | J57: 13 | K57: 0.076923077 | L57: 879 | M57: =IF($K57 < 0.15, "Not Scanned",IF($K57 < 0.55, "Partially Scanned",IF($K57 >= 0.55, "Fully Scanned","Not Found"))) -> Not Scanned | N57: 13 | O57: 0.076923077 | P57: 879 | Q57: =IF($K57 < 0.15, "Not Scanned",IF($K57 < 0.55, "Partially Scanned",IF($K57 >= 0.55, "Fully Scanned","Not Found"))) -> Not Scanned
A58: 216 | B58: https://modernslaveryregister.gov.au/statements/216/ | C58: =VLOOKUP($A58,Sheet1!$A$2:$I$6793,2,FALSE) -> Joint | D58: =VLOOKUP($A58,Sheet1!$A$2:$I$6793,3,FALSE) -> Australia | F58: 1BN+ | G58: FIRST SENTIER INVESTORS ASIA HOLDINGS LTD (54 054 571 701), FIRST SENTIER INVESTORS (AUSTRALIA) IM LTD (89 114 194 311), FIRST SENTIER INVESTORS (AUSTRALIA) INFRASTRUCTURE HOLDINGS LTD (20 085 313 926), FIRST SENTIER INVESTORS (AUSTRALIA) RE LTD (13 006 464 428), FIRST SENTIER INVESTORS (AUSTRALIA) SERVICES PTY LTD (73 624 305 595), FIRST SENTIER INVESTORS HOLDINGS PTY LTD (49 630 725 558), FIRST SENTIER INVESTORS REALINDEX PTY LTD (24 133 312 017), First State Investments (Hong Kong) Ltd | H58: Financial, insurance and real estate activities | I58: United Kingdom Modern Slavery Act 2015 | J58: 9 | K58: 0.11111111 | L58: 394 | M58: =IF($K58 < 0.15, "Not Scanned",IF($K58 < 0.55, "Partially Scanned",IF($K58 >= 0.55, "Fully Scanned","Not Found"))) -> Not Scanned | N58: 9 | O58: 0.11111111 | P58: 394 | Q58: =IF($K58 < 0.15, "Not Scanned",IF($K58 < 0.55, "Partially Scanned",IF($K58 >= 0.55, "Fully Scanned","Not Found"))) -> Not Scanned
A59: 218 | B59: https://modernslaveryregister.gov.au/statements/218/ | C59: =VLOOKUP($A59,Sheet1!$A$2:$I$6793,2,FALSE) -> Joint | D59: =VLOOKUP($A59,Sheet1!$A$2:$I$6793,3,FALSE) -> Australia | F59: 100-150M | G59: EnerMech Pty Limited (32 136 435 062), MINTEG PTY LTD (18 166 303 760) | J59: 6 | K59: 0 | L59: 397.5 | M59: =IF($K59 < 0.15, "Not Scanned",IF($K59 < 0.55, "Partially Scanned",IF($K59 >= 0.55, "Fully Scanned","Not Found"))) -> Not Scanned | N59: 6 | O59: 0 | P59: 397.5 | Q59: =IF($K59 < 0.15, "Not Scanned",IF($K59 < 0.55, "Partially Scanned",IF($K59 >= 0.55, "Fully Scanned","Not Found"))) -> Not Scanned
A60: 219 | B60: https://modernslaveryregister.gov.au/statements/219/ | C60: =VLOOKUP($A60,Sheet1!$A$2:$I$6793,2,FALSE) -> Joint | D60: =VLOOKUP($A60,Sheet1!$A$2:$I$6793,3,FALSE) -> Australia, New Zealand | E60: Datacom, Datacom Connect | F60: 500-600M | G60: DATACOM AUSTRALIA HOLDINGS PTY LIMITED (45 094 235 373), DATACOM CONNECT PTY LTD (16 103 112 303), DATACOM DATA CENTRES PTY LTD (58 110 978 179), Datacom New Zealand Limited (95 875 120 116), DATACOM SYSTEMS (AU) PTY LTD (39 135 427 075) | J60: 9 | K60: 0 | L60: 364 | M60: =IF($K60 < 0.15, "Not Scanned",IF($K60 < 0.55, "Partially Scanned",IF($K60 >= 0.55, "Fully Scanned","Not Found"))) -> Not Scanned | N60: 9 | O60: 0 | P60: 364 | Q60: =IF($K60 < 0.15, "Not Scanned",IF($K60 < 0.55, "Partially Scanned",IF($K60 >= 0.55, "Fully Scanned","Not Found"))) -> Not Scanned
A61: 224 | B61: https://modernslaveryregister.gov.au/statements/224/ | C61: =VLOOKUP($A61,Sheet1!$A$2:$I$6793,2,FALSE) -> Joint | D61: =VLOOKUP($A61,Sheet1!$A$2:$I$6793,3,FALSE) -> Australia | E61: MACQUARIE GROUP LIMITED, MACQUARIE AMERICAS HOLDINGS PTY LTD, MACQUARIE ASSET MANAGEMENT HOLDINGS PTY LIMITED, MACQUARIE ASSET MANAGEMENT US HOLDINGS PTY LIMITED, MACQUARIE B.H. PTY LTD, MACQUARIE BANK LIMITED, MACQUARIE CAPITAL (AUSTRALIA) LIMITED, MACQUARIE CORPORATE AND ASSET FINANCE LIMITED, MACQUARIE CORPORATE FINANCE HOLDINGS PTY LIMITED, MACQUARIE CORPORATE FINANCE LIMITED, MACQUARIE CORPORATE HOLDINGS PTY LIMITED, MACQUARIE CORPORATE INTERNATIONAL HOLDINGS PTY LIMITED, MACQUARIE EMG HOLDINGS PTY LIMITED, MACQUARIE ENERGY HOLDINGS PTY LTD, MACQUARIE EQUITIES (US) HOLDINGS PTY. LIMITED, MACQUARIE FINANCE HOLDINGS LIMITED, MACQUARIE FINANCIAL HOLDINGS (USA) LLC, MACQUARIE FINANCIAL HOLDINGS PTY LIMITED, MACQUARIE FUNDING HOLDINGS LLC, MACQUARIE FUNDS MANAGEMENT HOLDINGS PTY LIMITED, MACQUARIE GROUP (US) HOLDINGS NO.1 PTY LTD, MACQUARIE GROUP SERVICES AUSTRALIA PTY LTD, MACQUARIE INFRASTRUCTURE AND REAL ASSETS HOLDINGS PTY LIMITED, MACQUARIE INFRASTRUCTURE FUNDS MANAGEMENT PTY LIMITED, MACQUARIE INTERNATIONAL INVESTMENTS PTY LIMITED, MACQUARIE INVESTMENT HOLDINGS NO.2 PTY LIMITED, MACQUARIE INVESTMENT HOLDINGS PTY LIMITED, MACQUARIE INVESTMENT MANAGEMENT AUSTRALIA LIMITED, MACQUARIE INVESTMENT MANAGEMENT HOLDINGS PTY LIMITED, MACQUARIE INVESTMENT MANAGEMENT LTD, MACQUARIE LEASING NSW PTY LTD, MACQUARIE LEASING PTY. LIMITED, MACQUARIE PRINCIPAL FINANCE PTY LIMITED, MACQUARIE SECURITIES (AUSTRALIA) LIMITED, MACQUARIE SECURITISATION LIMITED, MACQUARIE SERVICES (USA) LLC, MACQUARIE SPECIALISED ASSET MANAGEMENT LTD | F61: 1BN+ | G61: Macquarie Americas Holdings Pty Ltd (82 124 071 414), MACQUARIE ASSET MANAGEMENT HOLDINGS PTY LIMITED (84 134 474 712), MACQUARIE ASSET MANAGEMENT US HOLDINGS PTY LIMITED (72 637 679 102), MACQUARIE BANK LIMITED (46 008 583 542), Macquarie B.H. Pty Ltd (86 124 071 432), MACQUARIE CAPITAL (AUSTRALIA) LIMITED (79 123 199 548), MACQUARIE CORPORATE AND ASSET FINANCE LIMITED (49 006 198 910), MACQUARIE CORPORATE FINANCE HOLDINGS PTY LIMITED (96 008 606 862), MACQUARIE CORPORATE FINANCE LIMITED (71 008 595 426), MACQUARIE CORPORATE HOLDINGS PTY LIMITED (54 096 705 109), MACQUARIE CORPORATE INTERNATIONAL HOLDINGS PTY LIMITED (24 123 199 253), Macquarie EMG Holdings Pty Limited (27 127 185 719), Macquarie Energy Holdings Pty Ltd (46 122 300 592), MACQUARIE EQUITIES (US) HOLDINGS PTY. LIMITED (98 063 906 392), Macquarie Finance Holdings Limited (89 118 817 440), MACQUARIE FINANCIAL HOLDINGS PTY LIMITED (63 124 071 398), MACQUARIE FINANCIAL HOLDINGS (USA) LLC, MACQUARIE FUNDING HOLDINGS LLC, MACQUARIE FUNDS MANAGEMENT HOLDINGS PTY LIMITED (19 093 177 407), MACQUARIE GROUP LIMITED (94 122 169 279), MACQUARIE GROUP SERVICES AUSTRALIA PTY LTD (53 116 467 031), MACQUARIE GROUP (US) HOLDINGS NO.1 PTY LTD (61 124 071 389), MACQUARIE INFRASTRUCTURE AND REAL ASSETS HOLDINGS PTY LIMITED (95 082 018 399), MACQUARIE INFRASTRUCTURE FUNDS MANAGEMENT PTY LIMITED (54 074 311 390), Macquarie International Investments Pty Limited (28 108 590 996), MACQUARIE INVESTMENT HOLDINGS NO.2 PTY LIMITED (97 112 017 919), MACQUARIE INVESTMENT HOLDINGS PTY LIMITED (18 122 939 600), MACQUARIE INVESTMENT MANAGEMENT AUSTRALIA LIMITED (55 092 552 611), MACQUARIE INVESTMENT MANAGEMENT HOLDINGS PTY LIMITED (76 604 942 127), MACQUARIE INVESTMENT MANAGEMENT LTD (66 002 867 003), MACQUARIE LEASING NSW PTY LTD (67 002 675 032), MACQUARIE LEASING PTY LTD (38 002 674 982), MACQUARIE PRINCIPAL FINANCE PTY LIMITED (39 629 759 600), MACQUARIE SECURITIES (AUSTRALIA) LIMITED (58 002 832 126), MACQUARIE SECURITISATION LIMITED (16 003 297 336), MACQUARIE SERVICES (USA) LLC, MACQUARIE SPECIALISED ASSET MANAGEMENT LTD (71 087 382 965) | J61: 6 | K61: 0 | L61: 651 | M61: =IF($K61 < 0.15, "Not Scanned",IF($K61 < 0.55, "Partially Scanned",IF($K61 >= 0.55, "Fully Scanned","Not Found"))) -> Not Scanned | N61: 6 | O61: 0 | P61: 651 | Q61: =IF($K61 < 0.15, "Not Scanned",IF($K61 < 0.55, "Partially Scanned",IF($K61 >= 0.55, "Fully Scanned","Not Found"))) -> Not Scanned
A62: 225 | B62: https://modernslaveryregister.gov.au/statements/225/ | C62: =VLOOKUP($A62,Sheet1!$A$2:$I$6793,2,FALSE) -> Joint | D62: =VLOOKUP($A62,Sheet1!$A$2:$I$6793,3,FALSE) -> United Kingdom | E62: Baillie Gifford & Co | F62: 900M-1BN | G62: Baillie Gifford Overseas Limited | J62: 7 | K62: 0 | L62: 444 | M62: =IF($K62 < 0.15, "Not Scanned",IF($K62 < 0.55, "Partially Scanned",IF($K62 >= 0.55, "Fully Scanned","Not Found"))) -> Not Scanned | N62: 7 | O62: 0 | P62: 444 | Q62: =IF($K62 < 0.15, "Not Scanned",IF($K62 < 0.55, "Partially Scanned",IF($K62 >= 0.55, "Fully Scanned","Not Found"))) -> Not Scanned
A63: 226 | B63: https://modernslaveryregister.gov.au/statements/226/ | C63: =VLOOKUP($A63,Sheet1!$A$2:$I$6793,2,FALSE) -> Normal | D63: =VLOOKUP($A63,Sheet1!$A$2:$I$6793,3,FALSE) -> Germany | E63: 360T | F63: 100-150M | G63: 360 Treasury Systems AG | J63: 5 | K63: 1 | L63: 0 | M63: =IF($K63 < 0.15, "Not Scanned",IF($K63 < 0.55, "Partially Scanned",IF($K63 >= 0.55, "Fully Scanned","Not Found"))) -> Fully Scanned | N63: 5 | O63: 1 | P63: 0 | Q63: =IF($K63 < 0.15, "Not Scanned",IF($K63 < 0.55, "Partially Scanned",IF($K63 >= 0.55, "Fully Scanned","Not Found"))) -> Fully Scanned
A64: 227 | B64: https://modernslaveryregister.gov.au/statements/227/ | C64: =VLOOKUP($A64,Sheet1!$A$2:$I$6793,2,FALSE) -> Joint | D64: =VLOOKUP($A64,Sheet1!$A$2:$I$6793,3,FALSE) -> United Kingdom | E64: IGT, International Game Technology | F64: 0-99M | G64: I G T (AUSTRALIA) PTY LTD (65 002 904 690) | J64: 7 | K64: 0 | L64: 328 | M64: =IF($K64 < 0.15, "Not Scanned",IF($K64 < 0.55, "Partially Scanned",IF($K64 >= 0.55, "Fully Scanned","Not Found"))) -> Not Scanned | N64: 7 | O64: 0 | P64: 328 | Q64: =IF($K64 < 0.15, "Not Scanned",IF($K64 < 0.55, "Partially Scanned",IF($K64 >= 0.55, "Fully Scanned","Not Found"))) -> Not Scanned
A65: 228 | B65: https://modernslaveryregister.gov.au/statements/228/ | C65: =VLOOKUP($A65,Sheet1!$A$2:$I$6793,2,FALSE) -> Joint | D65: =VLOOKUP($A65,Sheet1!$A$2:$I$6793,3,FALSE) -> Australia | E65: KFC, Taco Bell | F65: 150-200M | G65: QSR PTY LTD (63 089 163 682) | J65: 6 | K65: 0 | L65: 331.5 | M65: =IF($K65 < 0.15, "Not Scanned",IF($K65 < 0.55, "Partially Scanned",IF($K65 >= 0.55, "Fully Scanned","Not Found"))) -> Not Scanned | N65: 6 | O65: 0 | P65: 331.5 | Q65: =IF($K65 < 0.15, "Not Scanned",IF($K65 < 0.55, "Partially Scanned",IF($K65 >= 0.55, "Fully Scanned","Not Found"))) -> Not Scanned
A66: 230 | B66: https://modernslaveryregister.gov.au/statements/230/ | C66: =VLOOKUP($A66,Sheet1!$A$2:$I$6793,2,FALSE) -> Joint | D66: =VLOOKUP($A66,Sheet1!$A$2:$I$6793,3,FALSE) -> Australia | E66: Boral, USG Boral Australia, Boral North America | F66: 1BN+ | G66: BORAL LIMITED (13 008 421 761), USG BORAL BUILDING PRODUCTS PTY LIMITED (84 004 231 976) | J66: 16 | K66: 0.0625 | L66: 332.5 | M66: =IF($K66 < 0.15, "Not Scanned",IF($K66 < 0.55, "Partially Scanned",IF($K66 >= 0.55, "Fully Scanned","Not Found"))) -> Not Scanned | N66: 16 | O66: 0.0625 | P66: 332.5 | Q66: =IF($K66 < 0.15, "Not Scanned",IF($K66 < 0.55, "Partially Scanned",IF($K66 >= 0.55, "Fully Scanned","Not Found"))) -> Not Scanned
A67: 231 | B67: https://modernslaveryregister.gov.au/statements/231/ | C67: =VLOOKUP($A67,Sheet1!$A$2:$I$6793,2,FALSE) -> Joint | D67: =VLOOKUP($A67,Sheet1!$A$2:$I$6793,3,FALSE) -> United States of America | E67: McCormick Foods Australia, Botanical Food Company | F67: 100-150M | G67: BOTANICAL FOOD COMPANY PTY LTD (47 085 074 282), MCCORMICK FOODS AUSTRALIA PTY. LTD. (62 004 763 259) | J67: 5 | K67: 1 | L67: 0 | M67: =IF($K67 < 0.15, "Not Scanned",IF($K67 < 0.55, "Partially Scanned",IF($K67 >= 0.55, "Fully Scanned","Not Found"))) -> Fully Scanned | N67: 5 | O67: 1 | P67: 0 | Q67: =IF($K67 < 0.15, "Not Scanned",IF($K67 < 0.55, "Partially Scanned",IF($K67 >= 0.55, "Fully Scanned","Not Found"))) -> Fully Scanned
A68: 235 | B68: https://modernslaveryregister.gov.au/statements/235/ | C68: =VLOOKUP($A68,Sheet1!$A$2:$I$6793,2,FALSE) -> Normal | D68: =VLOOKUP($A68,Sheet1!$A$2:$I$6793,3,FALSE) -> Australia | E68: McGuigan Wines, Tempus Two, Nepenthe, Barossa Valley Wine Company, Austflavor | F68: 250-300M | G68: AUSTRALIAN VINTAGE LTD (78 052 179 932) | J68: 6 | K68: 0 | L68: 352 | M68: =IF($K68 < 0.15, "Not Scanned",IF($K68 < 0.55, "Partially Scanned",IF($K68 >= 0.55, "Fully Scanned","Not Found"))) -> Not Scanned | N68: 6 | O68: 0 | P68: 352 | Q68: =IF($K68 < 0.15, "Not Scanned",IF($K68 < 0.55, "Partially Scanned",IF($K68 >= 0.55, "Fully Scanned","Not Found"))) -> Not Scanned
A69: 238 | B69: https://modernslaveryregister.gov.au/statements/238/ | C69: =VLOOKUP($A69,Sheet1!$A$2:$I$6793,2,FALSE) -> Joint | D69: =VLOOKUP($A69,Sheet1!$A$2:$I$6793,3,FALSE) -> Australia | E69: 3Sun, Aspinwall & Co, Enviros, Access Inspection Development, Colin Buchanan and Partners, Ingen, Performance Improvements Group, Primat, RRC Controls Services, Scopus Engineering, Specialist Equipment Solutions | F69: 1BN+ | G69: ADVISIAN PTY LTD (50 098 008 818), ENERGY RESOURCING AUSTRALIA PTY LIMITED (27 076 232 605), INTECSEA PTY LTD (18 008 961 260), WORLEY ECR PTY LTD (95 631 041 195), WORLEY ENGINEERING PTY LIMITED (19 008 876 284), WORLEY LIMITED (17 096 090 158), WORLEYPARSONS FINANCIAL SERVICES PTY LIMITED (34 099 425 831), WORLEY SERVICES PTY LIMITED (61 001 279 812) | J69: 11 | K69: 0.18181818 | L69: 232 | M69: =IF($K69 < 0.15, "Not Scanned",IF($K69 < 0.55, "Partially Scanned",IF($K69 >= 0.55, "Fully Scanned","Not Found"))) -> Partially Scanned | N69: 11 | O69: 0.18181818 | P69: 232 | Q69: =IF($K69 < 0.15, "Not Scanned",IF($K69 < 0.55, "Partially Scanned",IF($K69 >= 0.55, "Fully Scanned","Not Found"))) -> Partially Scanned
A70: 241 | B70: https://modernslaveryregister.gov.au/statements/241/ | C70: =VLOOKUP($A70,Sheet1!$A$2:$I$6793,2,FALSE) -> Normal | D70: =VLOOKUP($A70,Sheet1!$A$2:$I$6793,3,FALSE) -> Australia, New Zealand | E70: SRG Global Civil, SRG Global Facades, SRG Global Products, SRG Global Services, SRG Global Mining, SRG Global Integrated Services | F70: 500-600M | G70: SRG GLOBAL LIMITED (81 104 662 259) | J70: 12 | K70: 0.25 | L70: 185 | M70: =IF($K70 < 0.15, "Not Scanned",IF($K70 < 0.55, "Partially Scanned",IF($K70 >= 0.55, "Fully Scanned","Not Found"))) -> Partially Scanned | N70: 12 | O70: 0.25 | P70: 185 | Q70: =IF($K70 < 0.15, "Not Scanned",IF($K70 < 0.55, "Partially Scanned",IF($K70 >= 0.55, "Fully Scanned","Not Found"))) -> Partially Scanned
A71: 242 | B71: https://modernslaveryregister.gov.au/statements/242/ | C71: =VLOOKUP($A71,Sheet1!$A$2:$I$6793,2,FALSE) -> Normal | D71: =VLOOKUP($A71,Sheet1!$A$2:$I$6793,3,FALSE) -> Australia | F71: 150-200M | G71: SUMITOMO AUSTRALIA PTY LTD (81 000 371 497) | J71: 2 | K71: 0 | L71: 745 | M71: =IF($K71 < 0.15, "Not Scanned",IF($K71 < 0.55, "Partially Scanned",IF($K71 >= 0.55, "Fully Scanned","Not Found"))) -> Not Scanned | N71: 2 | O71: 0 | P71: 745 | Q71: =IF($K71 < 0.15, "Not Scanned",IF($K71 < 0.55, "Partially Scanned",IF($K71 >= 0.55, "Fully Scanned","Not Found"))) -> Not Scanned
A72: 248 | B72: https://modernslaveryregister.gov.au/statements/248/ | C72: =VLOOKUP($A72,Sheet1!$A$2:$I$6793,2,FALSE) -> Normal | D72: =VLOOKUP($A72,Sheet1!$A$2:$I$6793,3,FALSE) -> Australia | E72: Hit Network, Triple M, PodcastOne Australia | F72: 500-600M | G72: SOUTHERN CROSS MEDIA GROUP LIMITED (91 116 024 536) | J72: 4 | K72: 0.25 | L72: 393 | M72: =IF($K72 < 0.15, "Not Scanned",IF($K72 < 0.55, "Partially Scanned",IF($K72 >= 0.55, "Fully Scanned","Not Found"))) -> Partially Scanned | N72: 4 | O72: 0.25 | P72: 393 | Q72: =IF($K72 < 0.15, "Not Scanned",IF($K72 < 0.55, "Partially Scanned",IF($K72 >= 0.55, "Fully Scanned","Not Found"))) -> Partially Scanned
A73: 249 | B73: https://modernslaveryregister.gov.au/statements/249/ | C73: =VLOOKUP($A73,Sheet1!$A$2:$I$6793,2,FALSE) -> Normal | D73: =VLOOKUP($A73,Sheet1!$A$2:$I$6793,3,FALSE) -> Australia | E73: Redox | F73: 700-800M | G73: REDOX GROUP PTY LTD (42 627 118 101) | J73: 7 | K73: 1 | L73: 0 | M73: =IF($K73 < 0.15, "Not Scanned",IF($K73 < 0.55, "Partially Scanned",IF($K73 >= 0.55, "Fully Scanned","Not Found"))) -> Fully Scanned | N73: 7 | O73: 1 | P73: 0 | Q73: =IF($K73 < 0.15, "Not Scanned",IF($K73 < 0.55, "Partially Scanned",IF($K73 >= 0.55, "Fully Scanned","Not Found"))) -> Fully Scanned
A74: 254 | B74: https://modernslaveryregister.gov.au/statements/254/ | C74: =VLOOKUP($A74,Sheet1!$A$2:$I$6793,2,FALSE) -> Normal | D74: =VLOOKUP($A74,Sheet1!$A$2:$I$6793,3,FALSE) -> Australia | E74: Arrotex Australia Holdings Pty Ltd, Arrotex Australia Group Pty Ltd, Arrotex Pharmaceuticals Pty Ltd, Generic Partners Holding Co Pty Ltd, Generic Partners Pty Ltd, Apotex Australia Pty Limited, Apotex Pty Ltd, Arrow Pharmaceuticals Pty Ltd, Arrow Pharma Pty Ltd, Arrotex Investment Holdings 1 Pty Ltd, Pharmacy Alliance Investments Pty Ltd, Oraderm Pharmaceuticals Pty Ltd, ALW Health Pty Ltd, Amneal Pharmaceuticals Pty Ltd, Australian Pharmacy Buying Association Pty Ltd, Pharmacy Alliance Group Holdings Pty Ltd, Alliance Pharmacy Pty Ltd, Smarterpharm Pty Ltd, MyPak Solutions Australia Pty Ltd, Amneal Pharma Australia Pty Ltd, MyPak Solutions Pty Ltd, Practisoft Pty Limited | F74: Unknown | G74: ARROTEX HOLDINGS PTY LTD (47 630 331 814) | J74: 5 | K74: 0.2 | L74: 416 | M74: =IF($K74 < 0.15, "Not Scanned",IF($K74 < 0.55, "Partially Scanned",IF($K74 >= 0.55, "Fully Scanned","Not Found"))) -> Partially Scanned | N74: 5 | O74: 0.2 | P74: 416 | Q74: =IF($K74 < 0.15, "Not Scanned",IF($K74 < 0.55, "Partially Scanned",IF($K74 >= 0.55, "Fully Scanned","Not Found"))) -> Partially Scanned
A75: 259 | B75: https://modernslaveryregister.gov.au/statements/259/ | C75: =VLOOKUP($A75,Sheet1!$A$2:$I$6793,2,FALSE) -> Joint | D75: =VLOOKUP($A75,Sheet1!$A$2:$I$6793,3,FALSE) -> United States of America | E75: HP | F75: 450-500M | G75: HP PPS AUSTRALIA PTY LTD (16 603 480 628) | J75: 8 | K75: 0 | L75: 514 | M75: =IF($K75 < 0.15, "Not Scanned",IF($K75 < 0.55, "Partially Scanned",IF($K75 >= 0.55, "Fully Scanned","Not Found"))) -> Not Scanned | N75: 8 | O75: 0 | P75: 514 | Q75: =IF($K75 < 0.15, "Not Scanned",IF($K75 < 0.55, "Partially Scanned",IF($K75 >= 0.55, "Fully Scanned","Not Found"))) -> Not Scanned
A76: 261 | B76: https://modernslaveryregister.gov.au/statements/261/ | C76: =VLOOKUP($A76,Sheet1!$A$2:$I$6793,2,FALSE) -> Normal | D76: =VLOOKUP($A76,Sheet1!$A$2:$I$6793,3,FALSE) -> Australia | E76: ISPT Pty Ltd | F76: 500-600M | G76: ISPT Core Fund | J76: 22 | K76: 0.045454545 | L76: 388 | M76: =IF($K76 < 0.15, "Not Scanned",IF($K76 < 0.55, "Partially Scanned",IF($K76 >= 0.55, "Fully Scanned","Not Found"))) -> Not Scanned | N76: 22 | O76: 0.045454545 | P76: 388 | Q76: =IF($K76 < 0.15, "Not Scanned",IF($K76 < 0.55, "Partially Scanned",IF($K76 >= 0.55, "Fully Scanned","Not Found"))) -> Not Scanned
A77: 262 | B77: https://modernslaveryregister.gov.au/statements/262/ | C77: =VLOOKUP($A77,Sheet1!$A$2:$I$6793,2,FALSE) -> Normal | D77: =VLOOKUP($A77,Sheet1!$A$2:$I$6793,3,FALSE) -> Australia | E77: The Bloomfield Group | F77: 450-500M | G77: BIG BEN HOLDINGS PTY. LIMITED (63 008 434 562) | J77: 9 | K77: 0.22222222 | L77: 118 | M77: =IF($K77 < 0.15, "Not Scanned",IF($K77 < 0.55, "Partially Scanned",IF($K77 >= 0.55, "Fully Scanned","Not Found"))) -> Partially Scanned | N77: 9 | O77: 0.22222222 | P77: 118 | Q77: =IF($K77 < 0.15, "Not Scanned",IF($K77 < 0.55, "Partially Scanned",IF($K77 >= 0.55, "Fully Scanned","Not Found"))) -> Partially Scanned
A78: 265 | B78: https://modernslaveryregister.gov.au/statements/265/ | C78: =VLOOKUP($A78,Sheet1!$A$2:$I$6793,2,FALSE) -> Normal | D78: =VLOOKUP($A78,Sheet1!$A$2:$I$6793,3,FALSE) -> Australia | E78: Endeavour Energy | F78: 1BN+ | G78: The Trustee for Edwards O Trust & Others (11 247 365 823) | J78: 8 | K78: 0.125 | L78: 204 | M78: =IF($K78 < 0.15, "Not Scanned",IF($K78 < 0.55, "Partially Scanned",IF($K78 >= 0.55, "Fully Scanned","Not Found"))) -> Not Scanned | N78: 8 | O78: 0.125 | P78: 204 | Q78: =IF($K78 < 0.15, "Not Scanned",IF($K78 < 0.55, "Partially Scanned",IF($K78 >= 0.55, "Fully Scanned","Not Found"))) -> Not Scanned
A79: 268 | B79: https://modernslaveryregister.gov.au/statements/268/ | C79: =VLOOKUP($A79,Sheet1!$A$2:$I$6793,2,FALSE) -> Joint | D79: =VLOOKUP($A79,Sheet1!$A$2:$I$6793,3,FALSE) -> Australia | F79: Unknown | G79: SIGMA HEALTHCARE LIMITED (15 088 417 403) | J79: 5 | K79: 0.2 | L79: 311 | M79: =IF($K79 < 0.15, "Not Scanned",IF($K79 < 0.55, "Partially Scanned",IF($K79 >= 0.55, "Fully Scanned","Not Found"))) -> Partially Scanned | N79: 5 | O79: 0.2 | P79: 311 | Q79: =IF($K79 < 0.15, "Not Scanned",IF($K79 < 0.55, "Partially Scanned",IF($K79 >= 0.55, "Fully Scanned","Not Found"))) -> Partially Scanned
A80: 272 | B80: https://modernslaveryregister.gov.au/statements/272/ | C80: =VLOOKUP($A80,Sheet1!$A$2:$I$6793,2,FALSE) -> Joint | D80: =VLOOKUP($A80,Sheet1!$A$2:$I$6793,3,FALSE) -> Australia, United Kingdom | E80: Ashurst LLP, Ashurst Australia | F80: 1BN+ | G80: Ashurst Australia (75 304 286 095), Ashurst Australia Services Pty. Limited (45 001 687 618), Ashurst Business Services Limited, Ashurst LLP | J80: 4 | K80: 0 | L80: 452.5 | M80: =IF($K80 < 0.15, "Not Scanned",IF($K80 < 0.55, "Partially Scanned",IF($K80 >= 0.55, "Fully Scanned","Not Found"))) -> Not Scanned | N80: 4 | O80: 0 | P80: 452.5 | Q80: =IF($K80 < 0.15, "Not Scanned",IF($K80 < 0.55, "Partially Scanned",IF($K80 >= 0.55, "Fully Scanned","Not Found"))) -> Not Scanned
A81: 276 | B81: https://modernslaveryregister.gov.au/statements/276/ | C81: =VLOOKUP($A81,Sheet1!$A$2:$I$6793,2,FALSE) -> Normal | D81: =VLOOKUP($A81,Sheet1!$A$2:$I$6793,3,FALSE) -> Australia | E81: Crawford, Crawford & Company, Broadspire Australia, Crawford Contractor Connection, WeGoLook, Crawford Global Technical Services, Crawford Claim Solutions | F81: 0-99M | G81: CRAWFORD & COMPANY (AUSTRALIA) PTY. LTD. (11 002 317 133) | J81: 3 | K81: 0 | L81: 326 | M81: =IF($K81 < 0.15, "Not Scanned",IF($K81 < 0.55, "Partially Scanned",IF($K81 >= 0.55, "Fully Scanned","Not Found"))) -> Not Scanned | N81: 3 | O81: 0 | P81: 326 | Q81: =IF($K81 < 0.15, "Not Scanned",IF($K81 < 0.55, "Partially Scanned",IF($K81 >= 0.55, "Fully Scanned","Not Found"))) -> Not Scanned
A82: 277 | B82: https://modernslaveryregister.gov.au/statements/277/ | C82: =VLOOKUP($A82,Sheet1!$A$2:$I$6793,2,FALSE) -> Joint | D82: =VLOOKUP($A82,Sheet1!$A$2:$I$6793,3,FALSE) -> Australia | E82: Ramsay Health Care | F82: 1BN+ | G82: AFFINITY HEALTH PTY LIMITED (53 106 722 347), AH Holdings Health Care Pty Limited (36 115 549 230), Alpha Healthcare Pty Limited (74 000 727 882), ALPHA WESTMEAD PRIVATE HOSPITAL PTY LIMITED (99 083 874 597), AME Hospitals Pty Limited, AME Properties Pty Limited, AUSTRALIAN HOSPITAL CARE (PINDARA) PTY. LTD. (51 005 288 095), AUSTRALIAN HOSPITAL CARE PTY LIMITED (67 072 273 931), AUSTRALIAN MEDICAL ENTERPRISES PTY LIMITED (88 053 639 160), BENCHMARK HEALTHCARE HOLDINGS PTY LIMITED (34 084 168 276), BENCHMARK HEALTHCARE PTY LTD (47 058 174 619), Benchmark - Peninsula Pty Limited, Benchmark - Surrey Pty Limited, C&P Hospitals Holdings Pty Limited (16 106 722 570), HCOA HOSPITAL HOLDINGS (AUSTRALIA) PTY LIMITED (84 079 097 528), HCOA OPERATIONS (AUSTRALIA) PTY LIMITED (85 083 035 661), HEALTH CARE CORPORATION PTY LTD (91 000 392 101), HOSPITAL CORPORATION AUSTRALIA PTY LTD (48 000 935 946), Joondalup Hospital Pty Limited (61 106 723 193), NORTH SHORE PRIVATE HOSPITAL PTY LIMITED (67 059 183 596), RAMSAY CENTAURI PTY LIMITED (77 096 070 156), RAMSAY HEALTH CARE AUSTRALIA PTY LIMITED (36 003 184 889), Ramsay Health Care Investments Pty Limited (44 078 881 473), RAMSAY HEALTH CARE LIMITED (57 001 288 768), THE BENCHMARK HOSPITAL GROUP PTY. LTD. (61 005 437 169), The Trustee for AME PROPERTY TRUST (36 529 022 683), The Trustee for AME TRUST (92 172 305 738), The Trustee for PENINSULA HOSPITAL UNIT TRUST (45 961 711 618) | J82: 14 | K82: 0.071428571 | L82: 326 | M82: =IF($K82 < 0.15, "Not Scanned",IF($K82 < 0.55, "Partially Scanned",IF($K82 >= 0.55, "Fully Scanned","Not Found"))) -> Not Scanned | N82: 14 | O82: 0.071428571 | P82: 326 | Q82: =IF($K82 < 0.15, "Not Scanned",IF($K82 < 0.55, "Partially Scanned",IF($K82 >= 0.55, "Fully Scanned","Not Found"))) -> Not Scanned
A83: 279 | B83: https://modernslaveryregister.gov.au/statements/279/ | C83: =VLOOKUP($A83,Sheet1!$A$2:$I$6793,2,FALSE) -> Normal | D83: =VLOOKUP($A83,Sheet1!$A$2:$I$6793,3,FALSE) -> Japan | E83: Fujitsu General Australia | F83: 250-300M | G83: FUJITSU GENERAL (AUST.) PTY LIMITED (55 001 229 554) | J83: 9 | K83: 0.11111111 | L83: 369 | M83: =IF($K83 < 0.15, "Not Scanned",IF($K83 < 0.55, "Partially Scanned",IF($K83 >= 0.55, "Fully Scanned","Not Found"))) -> Not Scanned | N83: 9 | O83: 0.11111111 | P83: 369 | Q83: =IF($K83 < 0.15, "Not Scanned",IF($K83 < 0.55, "Partially Scanned",IF($K83 >= 0.55, "Fully Scanned","Not Found"))) -> Not Scanned
A84: 281 | B84: https://modernslaveryregister.gov.au/statements/281/ | C84: =VLOOKUP($A84,Sheet1!$A$2:$I$6793,2,FALSE) -> Normal | D84: =VLOOKUP($A84,Sheet1!$A$2:$I$6793,3,FALSE) -> Australia | E84: Toyota | F84: 400-450M | G84: TOYOTA MATERIAL HANDLING AUSTRALIA PTY LIMITED (38 104 644 635) | J84: 4 | K84: 1 | L84: 0 | M84: =IF($K84 < 0.15, "Not Scanned",IF($K84 < 0.55, "Partially Scanned",IF($K84 >= 0.55, "Fully Scanned","Not Found"))) -> Fully Scanned | N84: 4 | O84: 1 | P84: 0 | Q84: =IF($K84 < 0.15, "Not Scanned",IF($K84 < 0.55, "Partially Scanned",IF($K84 >= 0.55, "Fully Scanned","Not Found"))) -> Fully Scanned
A85: 285 | B85: https://modernslaveryregister.gov.au/statements/285/ | C85: =VLOOKUP($A85,Sheet1!$A$2:$I$6793,2,FALSE) -> Normal | D85: =VLOOKUP($A85,Sheet1!$A$2:$I$6793,3,FALSE) -> Hong Kong | E85: Lenovo, Lenovo (Australia & New Zealand) Pty Limited, Lenovo International Cooperatif U.A., Lenovo Group Limited | F85: 800-900M | G85: LENOVO (AUSTRALIA & NEW ZEALAND) PTY LIMITED (70 112 394 411) | J85: 7 | K85: 0 | L85: 364 | M85: =IF($K85 < 0.15, "Not Scanned",IF($K85 < 0.55, "Partially Scanned",IF($K85 >= 0.55, "Fully Scanned","Not Found"))) -> Not Scanned | N85: 7 | O85: 0 | P85: 364 | Q85: =IF($K85 < 0.15, "Not Scanned",IF($K85 < 0.55, "Partially Scanned",IF($K85 >= 0.55, "Fully Scanned","Not Found"))) -> Not Scanned
A86: 286 | B86: https://modernslaveryregister.gov.au/statements/286/ | C86: =VLOOKUP($A86,Sheet1!$A$2:$I$6793,2,FALSE) -> Joint | D86: =VLOOKUP($A86,Sheet1!$A$2:$I$6793,3,FALSE) -> Australia | E86: Herbert Smith Freehills | F86: 700-800M | G86: EXCHANGE HOUSE SERVICES AUSTRALIA PTY LTD (75 091 861 835), HERBERT SMITH FREEHILLS (98 773 882 646) | J86: 3 | K86: 0 | L86: 678 | M86: =IF($K86 < 0.15, "Not Scanned",IF($K86 < 0.55, "Partially Scanned",IF($K86 >= 0.55, "Fully Scanned","Not Found"))) -> Not Scanned | N86: 3 | O86: 0 | P86: 678 | Q86: =IF($K86 < 0.15, "Not Scanned",IF($K86 < 0.55, "Partially Scanned",IF($K86 >= 0.55, "Fully Scanned","Not Found"))) -> Not Scanned
A87: 288 | B87: https://modernslaveryregister.gov.au/statements/288/ | C87: =VLOOKUP($A87,Sheet1!$A$2:$I$6793,2,FALSE) -> Joint | D87: =VLOOKUP($A87,Sheet1!$A$2:$I$6793,3,FALSE) -> Australia | E87: T.K. Maxx | F87: 700-800M | G87: TJX AUSTRALIA HOLDING COMPANY PTY LIMITED (58 605 889 843), TJX AUSTRALIA PTY LIMITED (73 000 171 764) | J87: 3 | K87: 0.33333333 | L87: 543 | M87: =IF($K87 < 0.15, "Not Scanned",IF($K87 < 0.55, "Partially Scanned",IF($K87 >= 0.55, "Fully Scanned","Not Found"))) -> Partially Scanned | N87: 3 | O87: 0.33333333 | P87: 543 | Q87: =IF($K87 < 0.15, "Not Scanned",IF($K87 < 0.55, "Partially Scanned",IF($K87 >= 0.55, "Fully Scanned","Not Found"))) -> Partially Scanned
A88: 290 | B88: https://modernslaveryregister.gov.au/statements/290/ | C88: =VLOOKUP($A88,Sheet1!$A$2:$I$6793,2,FALSE) -> Normal | D88: =VLOOKUP($A88,Sheet1!$A$2:$I$6793,3,FALSE) -> Australia | E88: VISSF | F88: 150-200M | G88: THE VICTORIAN INDEPENDENT SCHOOLS SUPERANNUATION FUND (37 024 873 660) | J88: 1 | K88: 0 | L88: 428 | M88: =IF($K88 < 0.15, "Not Scanned",IF($K88 < 0.55, "Partially Scanned",IF($K88 >= 0.55, "Fully Scanned","Not Found"))) -> Not Scanned | N88: 1 | O88: 0 | P88: 428 | Q88: =IF($K88 < 0.15, "Not Scanned",IF($K88 < 0.55, "Partially Scanned",IF($K88 >= 0.55, "Fully Scanned","Not Found"))) -> Not Scanned
A89: 291 | B89: https://modernslaveryregister.gov.au/statements/291/ | C89: =VLOOKUP($A89,Sheet1!$A$2:$I$6793,2,FALSE) -> Joint | D89: =VLOOKUP($A89,Sheet1!$A$2:$I$6793,3,FALSE) -> Australia | E89: • Sumisho Coal Development Queensland Pty Ltd (ACN 082 435 149), • Ocean Coal Mining Pty Ltd (ACN 156 473 924), • SCAP Oaky Creek Pty Ltd (ACN 073 072 205), • SCAP Pentland Pty Ltd (ACN 079 624 570), • SCAP Wandoan Pty Ltd (ACN 079 136 968), • SCAP Redrock Pty Ltd (ACN 089 519 791), • SCAP Exploration Pty Ltd (ACN 663 910 764), • SCAP Hillalong Pty Ltd (ACN 637 374 059) | F89: 350-400M | G89: SUMISHO COAL AUSTRALIA HOLDINGS PTY LTD (71 057 890 865) | J89: 3 | K89: 0 | L89: 491 | M89: =IF($K89 < 0.15, "Not Scanned",IF($K89 < 0.55, "Partially Scanned",IF($K89 >= 0.55, "Fully Scanned","Not Found"))) -> Not Scanned | N89: 3 | O89: 0 | P89: 491 | Q89: =IF($K89 < 0.15, "Not Scanned",IF($K89 < 0.55, "Partially Scanned",IF($K89 >= 0.55, "Fully Scanned","Not Found"))) -> Not Scanned
A90: 293 | B90: https://modernslaveryregister.gov.au/statements/293/ | C90: =VLOOKUP($A90,Sheet1!$A$2:$I$6793,2,FALSE) -> Normal | D90: =VLOOKUP($A90,Sheet1!$A$2:$I$6793,3,FALSE) -> Australia | E90: SUMISHO COAL AUSTRALIA PTY LIMITED | F90: 150-200M | G90: SUMISHO COAL AUSTRALIA PTY LIMITED (30 061 524 249) | J90: 3 | K90: 0 | L90: 482 | M90: =IF($K90 < 0.15, "Not Scanned",IF($K90 < 0.55, "Partially Scanned",IF($K90 >= 0.55, "Fully Scanned","Not Found"))) -> Not Scanned | N90: 3 | O90: 0 | P90: 482 | Q90: =IF($K90 < 0.15, "Not Scanned",IF($K90 < 0.55, "Partially Scanned",IF($K90 >= 0.55, "Fully Scanned","Not Found"))) -> Not Scanned
A91: 295 | B91: https://modernslaveryregister.gov.au/statements/295/ | C91: =VLOOKUP($A91,Sheet1!$A$2:$I$6793,2,FALSE) -> Normal | D91: =VLOOKUP($A91,Sheet1!$A$2:$I$6793,3,FALSE) -> Australia | E91: QNP | F91: 150-200M | G91: QUEENSLAND NITRATES PTY LTD (63 079 889 268) | J91: 2 | K91: 0 | L91: 452 | M91: =IF($K91 < 0.15, "Not Scanned",IF($K91 < 0.55, "Partially Scanned",IF($K91 >= 0.55, "Fully Scanned","Not Found"))) -> Not Scanned | N91: 2 | O91: 0 | P91: 452 | Q91: =IF($K91 < 0.15, "Not Scanned",IF($K91 < 0.55, "Partially Scanned",IF($K91 >= 0.55, "Fully Scanned","Not Found"))) -> Not Scanned
... A98: 306 | B98: https://modernslaveryregister.gov.au/statements/306/ | C98: =VLOOKUP($A98,Sheet1!$A$2:$I$6793,2,FALSE) -> Normal | D98: =VLOOKUP($A98,Sheet1!$A$2:$I$6793,3,FALSE) -> Australia | E98: BRP, Can-Am, Sea-Doo, Ski-Doo, Lynx, Evinrude, Quintrex, Stacer, Savage, Yellowfin Plate | F98: Unknown | G98: BRP AUSTRALIA PTY LTD (64 097 370 100) | J98: 6 | K98: 0.33333333 | L98: 176.5 | M98: =IF($K98 < 0.15, "Not Scanned",IF($K98 < 0.55, "Partially Scanned",IF($K98 >= 0.55, "Fully Scanned","Not Found"))) -> Partially Scanned | N98: 6 | O98: 0.33333333 | P98: 176.5 | Q98: =IF($K98 < 0.15, "Not Scanned",IF($K98 < 0.55, "Partially Scanned",IF($K98 >= 0.55, "Fully Scanned","Not Found"))) -> Partially Scanned
A99: 308 | B99: https://modernslaveryregister.gov.au/statements/308/ | C99: =VLOOKUP($A99,Sheet1!$A$2:$I$6793,2,FALSE) -> Normal | D99: =VLOOKUP($A99,Sheet1!$A$2:$I$6793,3,FALSE) -> Australia | F99: 450-500M | G99: JOHNS LYNG GROUP LIMITED (86 620 466 248) | J99: 12 | K99: 0.41666667 | L99: 72 | M99: =IF($K99 < 0.15, "Not Scanned",IF($K99 < 0.55, "Partially Scanned",IF($K99 >= 0.55, "Fully Scanned","Not Found"))) -> Partially Scanned | N99: 12 | O99: 0.41666667 | P99: 72 | Q99: =IF($K99 < 0.15, "Not Scanned",IF($K99 < 0.55, "Partially Scanned",IF($K99 >= 0.55, "Fully Scanned","Not Found"))) -> Partially Scanned
A100: 314 | B100: https://modernslaveryregister.gov.au/statements/314/ | C100: =VLOOKUP($A100,Sheet1!$A$2:$I$6793,2,FALSE) -> Normal | D100: =VLOOKUP($A100,Sheet1!$A$2:$I$6793,3,FALSE) -> United States of America | F100: 200-250M | G100: TECH DATA ADVANCED SOLUTIONS (ANZ) LIMITED (77 107 656 833) | J100: 10 | K100: 0.1 | L100: 337 | M100: =IF($K100 < 0.15, "Not Scanned",IF($K100 < 0.55, "Partially Scanned",IF($K100 >= 0.55, "Fully Scanned","Not Found"))) -> Not Scanned | N100: 10 | O100: 0.1 | P100: 337 | Q100: =IF($K100 < 0.15, "Not Scanned",IF($K100 < 0.55, "Partially Scanned",IF($K100 >= 0.55, "Fully Scanned","Not Found"))) -> Not Scanned
A101: 320 | B101: https://modernslaveryregister.gov.au/statements/320/ | C101: =VLOOKUP($A101,Sheet1!$A$2:$I$6793,2,FALSE) -> Joint | D101: =VLOOKUP($A101,Sheet1!$A$2:$I$6793,3,FALSE) -> United States of America | E101: PVH, Calvin Klein, Tommy Hilfiger | F101: Unknown | G101: PVH BRANDS AUSTRALIA PTY LIMITED (15 165 485 290), SUNSHINE A PTY LTD (86 631 684 770) | J101: 5 | K101: 0 | L101: 569 | M101: =IF($K101 < 0.15, "Not Scanned",IF($K101 < 0.55, "Partially Scanned",IF($K101 >= 0.55, "Fully Scanned","Not Found"))) -> Not Scanned | N101: 5 | O101: 0 | P101: 569 | Q101: =IF($K101 < 0.15, "Not Scanned",IF($K101 < 0.55, "Partially Scanned",IF($K101 >= 0.55, "Fully Scanned","Not Found"))) -> Not Scanned
A102: 321 | B102: https://modernslaveryregister.gov.au/statements/321/ | C102: =VLOOKUP($A102,Sheet1!$A$2:$I$6793,2,FALSE) -> Normal | D102: =VLOOKUP($A102,Sheet1!$A$2:$I$6793,3,FALSE) -> Australia | E102: EB Games, Zing Pop Culture | F102: Unknown | G102: ELECTRONICS BOUTIQUE AUSTRALIA PTY LIMITED (50 077 681 442) | J102: 18 | K102: 0.22222222 | L102: 92 | M102: =IF($K102 < 0.15, "Not Scanned",IF($K102 < 0.55, "Partially Scanned",IF($K102 >= 0.55, "Fully Scanned","Not Found"))) -> Partially Scanned | N102: 18 | O102: 0.22222222 | P102: 92 | Q102: =IF($K102 < 0.15, "Not Scanned",IF($K102 < 0.55, "Partially Scanned",IF($K102 >= 0.55, "Fully Scanned","Not Found"))) -> Partially Scanned
A103: 322 | B103: https://modernslaveryregister.gov.au/statements/322/ | C103: =VLOOKUP($A103,Sheet1!$A$2:$I$6793,2,FALSE) -> Normal | D103: =VLOOKUP($A103,Sheet1!$A$2:$I$6793,3,FALSE) -> Australia | E103: Weet-Bix, UP&GO, So Good | F103: 350-400M | G103: AUSTRALIAN HEALTH & NUTRITION ASSOCIATION LIMITED (63 096 452 872) | J103: 5 | K103: 0 | L103: 414 | M103: =IF($K103 < 0.15, "Not Scanned",IF($K103 < 0.55, "Partially Scanned",IF($K103 >= 0.55, "Fully Scanned","Not Found"))) -> Not Scanned | N103: 5 | O103: 0 | P103: 414 | Q103: =IF($K103 < 0.15, "Not Scanned",IF($K103 < 0.55, "Partially Scanned",IF($K103 >= 0.55, "Fully Scanned","Not Found"))) -> Not Scanned
A104: 325 | B104: https://modernslaveryregister.gov.au/statements/325/ | C104: =VLOOKUP($A104,Sheet1!$A$2:$I$6793,2,FALSE) -> Normal | D104: =VLOOKUP($A104,Sheet1!$A$2:$I$6793,3,FALSE) -> Australia | E104: Glue Store, Trend Imports | F104: 100-150M | G104: NEXT ATHLEISURE PTY. LIMITED (47 083 404 424) | J104: 4 | K104: 0 | L104: 514 | M104: =IF($K104 < 0.15, "Not Scanned",IF($K104 < 0.55, "Partially Scanned",IF($K104 >= 0.55, "Fully Scanned","Not Found"))) -> Not Scanned | N104: 4 | O104: 0 | P104: 514 | Q104: =IF($K104 < 0.15, "Not Scanned",IF($K104 < 0.55, "Partially Scanned",IF($K104 >= 0.55, "Fully Scanned","Not Found"))) -> Not Scanned
A105: 326 | B105: https://modernslaveryregister.gov.au/statements/326/ | C105: =VLOOKUP($A105,Sheet1!$A$2:$I$6793,2,FALSE) -> Joint | D105: =VLOOKUP($A105,Sheet1!$A$2:$I$6793,3,FALSE) -> United Kingdom | E105: CMC Markets | F105: 150-200M | G105: CMC MARKETS GROUP AUSTRALIA PTY LTD (99 128 774 890) | J105: 3 | K105: 1 | L105: 0 | M105: =IF($K105 < 0.15, "Not Scanned",IF($K105 < 0.55, "Partially Scanned",IF($K105 >= 0.55, "Fully Scanned","Not Found"))) -> Fully Scanned | N105: 3 | O105: 1 | P105: 0 | Q105: =IF($K105 < 0.15, "Not Scanned",IF($K105 < 0.55, "Partially Scanned",IF($K105 >= 0.55, "Fully Scanned","Not Found"))) -> Fully Scanned
A106: 332 | B106: https://modernslaveryregister.gov.au/statements/332/ | C106: =VLOOKUP($A106,Sheet1!$A$2:$I$6793,2,FALSE) -> Normal | D106: =VLOOKUP($A106,Sheet1!$A$2:$I$6793,3,FALSE) -> Australia | E106: Nova Systems, GVH, Geoplex, two10degrees, Nova Group Global | F106: 200-250M | G106: NOVA AEROSPACE PROPRIETARY LIMITED (11 090 818 214) | J106: 5 | K106: 0 | L106: 245 | M106: =IF($K106 < 0.15, "Not Scanned",IF($K106 < 0.55, "Partially Scanned",IF($K106 >= 0.55, "Fully Scanned","Not Found"))) -> Not Scanned | N106: 5 | O106: 0 | P106: 245 | Q106: =IF($K106 < 0.15, "Not Scanned",IF($K106 < 0.55, "Partially Scanned",IF($K106 >= 0.55, "Fully Scanned","Not Found"))) -> Not Scanned
...

Sheet Sheet1
A1: StatementId | B1: Type | C1: Countries | D1: Trademarks | E1: AnnualRevenue | F1: Entities | G1: Link | H1: IndustrySectors | I1: OverseasObligations
A2: 12365 | B2: Joint | C2: Germany | D2: HELLA | E2: 600-700M | F2: HELLA ASIA PACIFIC HOLDINGS PTY LTD (59 007 958 787), HELLA ASIA PACIFIC PTY LTD (46 004 516 947), HELLA AUSTRALIA PTY LTD (77 006 256 524) | G2: https://modernslaveryregister.gov.au/statements/12365/ | H2: Automotive, machinery and heavy electrical equipment | I2: United Kingdom Modern Slavery Act 2015
A3: 12355 | B3: Normal | C3: Australia | D3: Comcare | E3: 300-350M | F3: COMCARE AUSTRALIA (41 640 788 304) | G3: https://modernslaveryregister.gov.au/statements/12355/ | H3: Government Sector
A4: 12306 | B4: Joint | C4: Australia | D4: BOQ, VMA, ME, BOQ Business, BOQ Finance, BOQ Specialist | E4: 1BN+ | F4: BANK OF QUEENSLAND LIMITED (32 009 656 740), MEMBERS EQUITY BANK LIMITED (56 070 887 679) | G4: https://modernslaveryregister.gov.au/statements/12306/ | H4: Financial, insurance and real estate activities
A5: 12308 | B5: Joint | C5: Australia | E5: 450-500M | F5: HWLE CONSULTING PTY LTD (47 158 617 497), THE MARTINEZ HWL PRACTICE TRUST & THE EAST HWL PRACTICE TRUST & THE WARAT HWL PRACTICE TRUST & THE MARIN HWL PRACTICE TRUST & OTHERS (37 246 549 189) | G5: https://modernslaveryregister.gov.au/statements/12308/ | H5: Professional and administrative services and supplies, including legal, consulting and accounting services
A6: 12307 | B6: Normal | C6: Australia | E6: 100-150M | F6: CENTRAL GIPPSLAND HEALTH SERVICE (85 050 485 681) | G6: https://modernslaveryregister.gov.au/statements/12307/ | H6: Healthcare and pharmaceuticals
A7: 12294 | B7: Normal | C7: Australia | D7: AUSTRALIAN NO.1, GMP PHARMACEUTICALS PTY LIMITED | E7: 200-250M | F7: GMP PHARMACEUTICALS PTY LIMITED (80 063 353 006) | G7: https://modernslaveryregister.gov.au/statements/12294/ | H7: Healthcare and pharmaceuticals
A8: 9924 | B8: Joint | C8: Japan | D8: Miki House | E8: 150-200M | F8: MIKI SHOKO CO., LTD. | G8: https://modernslaveryregister.gov.au/statements/9924/ | H8: Fashion, textiles, apparel and luxury goods | I8: United Kingdom Modern Slavery Act 2015
A9: 11658 | B9: Joint | C9: Australia | E9: 1BN+ | F9: RESMED ASIA PACIFIC LIMITED (86 070 076 470), RESMED HOLDINGS PTY LTD (28 003 765 133), RESMED PTY LTD (30 003 765 142) | G9: https://modernslaveryregister.gov.au/statements/11658/ | H9: Durable consumer goods, including electronics and appliances, home furnishings and other accessories Information technology and telecommunication Healthcare and pharmaceuticals | I9: United Kingdom Modern Slavery Act 2015 California Transparency in Supply Chains Act 2010
A10: 11195 | B10: Normal | C10: Australia | D10: Karoon Energy Ltd | E10: 350-400M | F10: Karoon Energy Ltd (53 107 001 338) | G10: https://modernslaveryregister.gov.au/statements/11195/ | H10: Mining, metals, chemicals and resources (including oil and gas)
A11: 10580 | B11: Joint | C11: Australia | D11: Civil Contractors (Aust) Pty Ltd, Winslow Constructors Pty Ltd, Winslow Infrastructure Pty Ltd | E11: 900M-1BN | F11: WINSLOW CONSTRUCTORS PTY LTD (73 006 581 764), WINSLOW INFRASTRUCTURE PTY. LTD. (72 119 092 385) | G11: https://modernslaveryregister.gov.au/statements/10580/ | H11: Construction, civil engineering and building products
A12: 10683 | B12: Normal | C12: Japan | E12: 100-150M | F12: MUFG BANK, LTD. (75 103 418 882) | G12: https://modernslaveryregister.gov.au/statements/10683/ | H12: Financial, insurance and real estate activities | I12: United Kingdom Modern Slavery Act 2015
A13: 11151 | B13: Joint | C13: Australia | E13: 400-450M | F13: SCOTT'S REFRIGERATED FREIGHTWAYS PTY LTD (41 162 034 326), SCOTTSRL PTY LTD (64 112 854 912) | G13: https://modernslaveryregister.gov.au/statements/11151/ | H13: Transportation, logistics, and storage
A14: 12088 | B14: Joint | C14: Australia, United Kingdom, United States of America | D14: Pendal Group Limited, Pendal Fund Services Limited, Pendal Institutional Limited, JO Hambro Capital Management Limited, Regnan – Governance Research and Engagement Pty Ltd, Pendal UK Limited, Pendal USA Inc., Thompson Siegel & Walmsley LLC | E14: 1BN+ | F14: PENDAL FUND SERVICES LIMITED (13 161 249 332), PENDAL GROUP LIMITED (28 126 385 822), PENDAL INSTITUTIONAL LIMITED (17 126 390 627), Pendal UK Limited, Pendal USA Inc., Regnan - Governance Research and Engagement Pty Limited (93 125 320 041) | G14: https://modernslaveryregister.gov.au/statements/12088/ | H14: Financial, insurance and real estate activities | I14: United Kingdom Modern Slavery Act 2015
A15: 12086 | B15: Normal | C15: Australia | E15: 150-200M | F15: TOMRA CLEANAWAY PTY LIMITED (43 620 427 116) | G15: https://modernslaveryregister.gov.au/statements/12086/ | H15: Waste management and recycling
A16: 12085 | B16: Joint | C16: Australia | E16: 800-900M | F16: NICK SCALI LIMITED (82 000 403 896), PLUSH-THINK SOFAS PTY LTD (55 080 012 595) | G16: https://modernslaveryregister.gov.au/statements/12085/ | H16: Durable consumer goods, including electronics and appliances, home furnishings and other accessories
A17: 12084 | B17: Normal | C17: Australia | D17: Probiotec Limited, Probiotec Pharma, LJM Marketing Services, Multipack-LJM, South Pack Laboratories, ABS, HH Packaging | E17: 100-150M | F17: PROBIOTEC LIMITED (91 075 170 151) | G17: https://modernslaveryregister.gov.au/statements/12084/ | H17: Healthcare and pharmaceuticals
A18: 12081 | B18: Normal | C18: Australia | E18: 100-150M | F18: WELLWAYS AUSTRALIA LIMITED (93 093 357 165) | G18: https://modernslaveryregister.gov.au/statements/12081/ | H18: Charitable / not-for-profit activities
A19: 12076 | B19: Joint | C19: Australia | E19: 300-350M | F19: ROYAN GROUP BIDCO PTY LIMITED (56 638 670 470), ROYAN GROUP HOLDCO PTY LIMITED (91 638 670 238), ROYAN GROUP MIDCO PTY LIMITED (25 638 670 336) | G19: https://modernslaveryregister.gov.au/statements/12076/ | H19: Transportation, logistics, and storage
A20: 12075 | B20: Joint | C20: Australia | D20: FCM, Corporate Traveller, FLight Centre | E20: 1BN+ | F20: AUSTRALIAN OPCO PTY LTD (20 003 279 534), FLIGHT CENTRE TRAVEL GROUP LIMITED (25 003 377 188) | G20: https://modernslaveryregister.gov.au/statements/12075/ | H20: Consumer services, including accommodation, hospitality, tourism and leisure Education and research | I20: United Kingdom Modern Slavery Act 2015
A21: 12074 | B21: Normal | C21: Australia | D21: Fur Life Vet; Country Vet | E21: 150-200M | F21: APIAM ANIMAL HEALTH LIMITED (50 604 961 024) | G21: https://modernslaveryregister.gov.au/statements/12074/ | H21: Food and beverages, agriculture and fishing
A22: 12073 | B22: Normal | C22: Australia | E22: 1BN+ | F22: METRO TRAINS AUSTRALIA PTY LTD (88 614 061 960) | G22: https://modernslaveryregister.gov.au/statements/12073/ | H22: Transportation, logistics, and storage
A23: 12072 | B23: Joint | C23: Australia | D23: Fidelity | E23: 200-250M | F23: FIL INVESTMENT MANAGEMENT (AUSTRALIA) LIMITED (34 006 773 575), FIL Responsible Entity (Australia) Limited (33 148 059 009), The Trustee for Fidelity Wholesale Plus Australian Equities Fund (26 876 355 623) | G23: https://modernslaveryregister.gov.au/statements/12072/ | H23: Financial, insurance and real estate activities
A24: 12070 | B24: Joint | C24: Australia | D24: Credit Corp Group Limited, Credit Corp Financial Services Pty Limited, Collection House Limited, Credit Corp Services Pty Limited | E24: 800-900M | F24: COLLECTION HOUSE LIMITED (74 010 230 716), Credit Corp Financial Services Pty Limited (39 146 525 706), CREDIT CORP GROUP LIMITED (33 092 697 151), CREDIT CORP SERVICES PTY LIMITED (95 082 928 872) | G24: https://modernslaveryregister.gov.au/statements/12070/ | H24: Financial, insurance and real estate activities
A25: 11903 | B25: Joint | C25: Australia | D25: Ray White, Loan Market Group | E25: 1BN+ | F25: GROUP ADMINISTRATION AUSTRALIA PTY LTD (30 010 374 731), LOAN MARKET GROUP PTY LTD (83 105 221 967), MINGLECLIFF (QLD) PTY LTD & TUPMAN PTY. LTD. (21 464 496 649) | G25: https://modernslaveryregister.gov.au/statements/11903/ | H25: Financial, insurance and real estate activities
A26: 12069 | B26: Normal | C26: Australia | E26: 100-150M | F26: GENPACT AUSTRALIA PTY LTD (15 616 571 423) | G26: https://modernslaveryregister.gov.au/statements/12069/ | H26: Information technology and telecommunication Professional and administrative services and supplies, including legal, consulting and accounting services | I26: United Kingdom Modern Slavery Act 2015
A27: 12068 | B27: Normal | C27: Australia | D27: Linfox, Armaguard, Linfox Logistics | E27: Unknown | F27: LINFOX PROPRIETARY LIMITED (59 004 667 298) | G27: https://modernslaveryregister.gov.au/statements/12068/ | H27: Transportation, logistics, and storage
A28: 12067 | B28: Normal | C28: Australia | E28: 100-150M | F28: Magi Enterprises Pty Ltd (49 154 423 613) | G28: https://modernslaveryregister.gov.au/statements/12067/ | H28: Fashion, textiles, apparel and luxury goods
A29: 12066 | B29: Joint | C29: Australia, Singapore | D29: Civmec Construction & Engineering Pty Ltd, Civmec Construction & Engineering Singapore Pte Ltd, Civmec-MALA PNG Ltd, Civmec Holdings Pty Ltd, Multidiscipline Solutions Pty Ltd, Civmec Pipe Products Pty Ltd, Civmec Electrical & Instrumentation Pty Ltd, Civmec-DLG Pty Ltd, Forgacs Marine & Defence Pty Ltd Civmec, Civmec Construction & Engineering Africa Ltd, ForgacsValco Pty Ltd, Construction & Engineering Uganda Ltd | E29: 800-900M | F29: CIVMEC LIMITED (50 604 316 690) | G29: https://modernslaveryregister.gov.au/statements/12066/ | H29: Mining, metals, chemicals and resources (including oil and gas) Construction, civil engineering and building products Defence and aerospace
A30: 11869 | B30: Normal | C30: Australia | D30: Camilla Australia Pty Ltd | E30: 100-150M | F30: CAMILLA AUSTRALIA PTY LTD (67 135 300 382) | G30: https://modernslaveryregister.gov.au/statements/11869/ | H30: Fashion, textiles, apparel and luxury goods
A31: 12065 | B31: Normal | C31: Australia | E31: 100-150M | F31: PLE COMPUTERS PTY LTD (48 051 046 596) | G31: https://modernslaveryregister.gov.au/statements/12065/ | H31: Durable consumer goods, including electronics and appliances, home furnishings and other accessories
A32: 12064 | B32: Joint | C32: Australia | D32: Cromwell, Property Group, cromwell property group | E32: 1BN+ | F32: CROMWELL CORPORATION LIMITED (44 001 056 980), CROMWELL PROPERTY SECURITIES LIMITED (11 079 147 809) | G32: https://modernslaveryregister.gov.au/statements/12064/ | H32: Financial, insurance and real estate activities | I32: United Kingdom Modern Slavery Act 2015
A33: 12063 | B33: Normal | C33: Australia | E33: 100-150M | F33: Enviro Pipes Pty Ltd (84 130 666 518) | G33: https://modernslaveryregister.gov.au/statements/12063/ | H33: Other
A34: 12062 | B34: Normal | C34: Australia | D34: The Smith Family, VIEW Clubs of Australia | E34: 100-150M | F34: THE SMITH FAMILY (28 000 030 179) | G34: https://modernslaveryregister.gov.au/statements/12062/ | H34: Charitable / not-for-profit activities
A35: 11890 | B35: Joint | C35: Switzerland | E35: 1BN+ | F35: AMCOR FLEXIBLES (AUSTRALIA) PTY LTD (46 113 833 748), AMCOR FLEXIBLES GROUP PTY LTD (33 113 833 695), Amcor plc, AMCOR PTY LTD (62 000 017 372) | G35: https://modernslaveryregister.gov.au/statements/11890/ | H35: Forestry, timber products, paper and containers and packaging | I35: United Kingdom Modern Slavery Act 2015 California Transparency in Supply Chains Act 2010
A36: 12061 | B36: Joint | C36: Australia | D36: Ambrose Building, Ambrose Construct Group, Construct Services, Inserve, Inserve Australia | E36: 200-250M | F36: AMBROSE CONSTRUCT GROUP PTY LTD (35 131 176 102), Inserve Australia Ltd (76 147 747 859) | G36: https://modernslaveryregister.gov.au/statements/12061/ | H36: Construction, civil engineering and building products
A37: 12060 | B37: Normal | C37: Australia | D37: Domino's Pizza | E37: 1BN+ | F37: DOMINO'S PIZZA ENTERPRISES LIMITED (16 010 489 326) | G37: https://modernslaveryregister.gov.au/statements/12060/ | H37: Food and beverages, agriculture and fishing
A38: 12057 | B38: Normal | C38: Australia | D38: Boom Logistics, Boom | E38: 200-250M | F38: BOOM LOGISTICS LTD (28 095 466 961) | G38: https://modernslaveryregister.gov.au/statements/12057/ | H38: Mining, metals, chemicals and resources (including oil and gas) Automotive, machinery and heavy electrical equipment Construction, civil engineering and building products Transportation, logistics, and storage Other
A39: 12029 | B39: Normal | C39: Australia | E39: 100-150M | F39: SOUTHERN PORTS AUTHORITY (30 044 341 250) | G39: https://modernslaveryregister.gov.au/statements/12029/ | H39: Transportation, logistics, and storage
A40: 12056 | B40: Normal | C40: Australia | E40: 100-150M | F40: AUSTRALIAN STEEL TRADERS PTY LTD (93 644 181 028) | G40: https://modernslaveryregister.gov.au/statements/12056/ | H40: Mining, metals, chemicals and resources (including oil and gas)
A41: 12054 | B41: Normal | C41: Australia | E41: 100-150M | F41: ENERGY WORLD CORPORATION LTD (34 009 124 994) | G41: https://modernslaveryregister.gov.au/statements/12054/ | H41: Utilities: gas, water and electricity
A42: 12051 | B42: Normal | C42: Australia | E42: 100-150M | F42: P.V AATHREYA & Others (70 843 523 318) | G42: https://modernslaveryregister.gov.au/statements/12051/ | H42: Professional and administrative services and supplies, including legal, consulting and accounting services
A43: 11940 | B43: Joint | C43: Australia | D43: Harvey Beef, Ernest Green & Sons, Leeuwin Coast | E43: 800-900M | F43: HARVEST ROAD GROUP PTY LTD (31 169 138 014), Harvey Industries Group Pty Ltd (64 117 597 985) | G43: https://modernslaveryregister.gov.au/statements/11940/ | H43: Food and beverages, agriculture and fishing
A44: 12052 | B44: Normal | C44: Australia | D44: Milne Feeds, Mt Barker Free Range Farms | E44: 200-250M | F44: MILNE AGRIGROUP PTY LTD (92 008 919 579) | G44: https://modernslaveryregister.gov.au/statements/12052/ | H44: Food and beverages, agriculture and fishing
A45: 12004 | B45: Joint | C45: Australia | D45: Fidelity International | E45: 200-250M | F45: FIL INVESTMENT MANAGEMENT (AUSTRALIA) LIMITED (34 006 773 575), FIL Responsible Entity (Australia) Limited (33 148 059 009), THE TRUSTEE FOR FIDELITY AUSTRALIAN EQUITIES FUND (22 409 131 011) | G45: https://modernslaveryregister.gov.au/statements/12004/ | H45: Financial, insurance and real estate activities
A46: 12053 | B46: Joint | C46: Australia | E46: 600-700M | F46: Mader Contracting Pty Ltd (36 114 021 537), MADER GROUP LIMITED (51 159 340 397), MADER QUEENSLAND PTY LTD (86 611 004 552) | G46: https://modernslaveryregister.gov.au/statements/12053/ | H46: Mining, metals, chemicals and resources (including oil and gas)
A47: 12050 | B47: Normal | C47: Australia | D47: Carlisle Homes, Easy Living | E47: 450-500M | F47: CARLISLE HOMES PTY LTD (86 106 263 209) | G47: https://modernslaveryregister.gov.au/statements/12050/ | H47: Construction, civil engineering and building products
A48: 12048 | B48: Normal | C48: Australia, Botswana, Spain | D48: Sandfire, DeGrussa, Motheo, Black Butte, MATSA | E48: 900M-1BN | F48: SANDFIRE RESOURCES LIMITED (55 105 154 185) | G48: https://modernslaveryregister.gov.au/statements/12048/ | H48: Mining, metals, chemicals and resources (including oil and gas)
A49: 11584 | B49: Joint | C49: Australia | D49: Paynter Dixon Management Services Pty Limited, Paynter Dixon Pty Limited | E49: 0-99M | F49: PAYNTER DIXON MANAGEMENT SERVICES PTY LIMITED (96 097 318 084), PAYNTER DIXON PTY LIMITED (65 069 785 262) | G49: https://modernslaveryregister.gov.au/statements/11584/ | H49: Construction, civil engineering and building products
A50: 12046 | B50: Joint | C50: Australia | D50: ABC Bullion, ABC Refinery, Palloys, GoldenAge International, Custodian Vaults, W.J. Sanders | E50: 1BN+ | F50: ABC REFINERY (AUSTRALIA) PTY LIMITED (86 621 121 079), AUSTRALIAN BULLION COMPANY (N S W) PTY LTD (82 002 858 602) | G50: https://modernslaveryregister.gov.au/statements/12046/ | H50: Mining, metals, chemicals and resources (including oil and gas)
A51: 12045 | B51: Normal | C51: Australia | E51: 1BN+ | F51: SUTTONS INVESTMENTS PTY. LIMITED (84 008 446 428) | G51: https://modernslaveryregister.gov.au/statements/12045/ | H51: Automotive, machinery and heavy electrical equipment
A52: 12042 | B52: Normal | C52: Australia | D52: RSM Australia, RSM | E52: 200-250M | F52: THE TRUSTEE FOR BIRDANCO PRACTICE TRUST (65 319 382 479) | G52: https://modernslaveryregister.gov.au/statements/12042/ | H52: Professional and administrative services and supplies, including legal, consulting and accounting services
A53: 12040 | B53: Normal | C53: Australia | E53: 0-99M | F53: Vivienne Court Holdings Pty Ltd (86 153 821 446) | G53: https://modernslaveryregister.gov.au/statements/12040/ | H53: Financial, insurance and real estate activities
A54: 12039 | B54: Joint | C54: Australia | D54: Champions IGA | E54: 200-250M | F54: BMS RETAIL GROUP HOLDINGS PTY LTD (93 090 448 007) | G54: https://modernslaveryregister.gov.au/statements/12039/ | H54: Other
A55: 12033 | B55: Joint | C55: Australia | E55: 900M-1BN | F55: The Trustee for Retail Prodigy Group Trust (43 854 395 125), The Trustee for Retail Prodigy NZ Trust (65 490 082 738), The Trustee for Retail Prodigy Operations Trust (27 861 675 009), The Trustee for RPG Brands Trust (31 456 018 824), The Trustee for RPG Timbuk2 Unit Trust (59 762 211 688), The Trustee for RPG Toms Unit Trust (81 834 482 509) | G55: https://modernslaveryregister.gov.au/statements/12033/ | H55: Fashion, textiles, apparel and luxury goods
A56: 12031 | B56: Joint | C56: Australia | E56: 900M-1BN | F56: SILVER LAKE (DEFLECTOR) PTY LTD (72 101 224 999), Silver Lake Resources Limited (38 108 779 782) | G56: https://modernslaveryregister.gov.au/statements/12031/ | H56: Mining, metals, chemicals and resources (including oil and gas)
A57: 12030 | B57: Joint | C57: Australia, France, Ireland, United Kingdom, United States of America | D57: EML Payments Limited (EML), Prepaid Financial Services Limited (PFS), Sentenial Limited (Sentenial) | E57: 200-250M | F57: EML PAYMENTS LIMITED (93 104 757 904) | G57: https://modernslaveryregister.gov.au/statements/12030/ | H57: Other | I57: United Kingdom Modern Slavery Act 2015
A58: 12027 | B58: Joint | C58: Australia | D58: Green Leaves Early Learning Centres | E58: 100-150M | F58: GREEN LEAVES HOLDCO PTY LTD (78 655 049 120) | G58: https://modernslaveryregister.gov.au/statements/12027/ | H58: Other
A59: 12028 | B59: Normal | C59: Australia | D59: Riverland Smallgoods | E59: 300-350M | F59: D'ORSOGNA LIMITED (27 063 427 752) | G59: https://modernslaveryregister.gov.au/statements/12028/ | H59: Food and beverages, agriculture and fishing
A60: 12023 | B60: Joint | C60: Australia | D60: MONARCH, KABOODLE, INABOX | E60: 300-350M | F60: AUSTRALIA HOMEWARE ENTERPRISE PTY LTD (25 613 201 899), AUSTRALIAN BRUSHWARE CORPORATION PTY LTD (81 068 706 829), DIY RESOLUTIONS PTY LTD (72 103 688 679) | G60: https://modernslaveryregister.gov.au/statements/12023/ | H60: Forestry, timber products, paper and containers and packaging
A61: 12026 | B61: Normal | C61: Australia, Denmark, Ireland, Singapore, United Kingdom | E61: 300-350M | F61: Virtus Health Limited (80 129 643 492) | G61: https://modernslaveryregister.gov.au/statements/12026/ | H61: Healthcare and pharmaceuticals | I61: United Kingdom Modern Slavery Act 2015
A62: 12022 | B62: Normal | C62: Australia | D62: S. Smith & Son Pty Ltd, S. Smith & Son Processing Pty Ltd, Negociants International Pty Ltd, Free Run Juice Pty Ltd, Yalumba, Hill-Smith Family Estates, Jansz, Dalrymple, Oxford Landing, Pewsey Vale, Running with Bulls | E62: 250-300M | F62: SAMUEL SMITH & SON PTY. LTD. (64 007 534 278) | G62: https://modernslaveryregister.gov.au/statements/12022/ | H62: Food and beverages, agriculture and fishing
A63: 12025 | B63: Joint | C63: Australia | E63: 250-300M | F63: CATER CARE HOLDINGS PTY LTD (69 603 124 812) | G63: https://modernslaveryregister.gov.au/statements/12025/ | H63: Food and beverages, agriculture and fishing Consumer services, including accommodation, hospitality, tourism and leisure
A64: 12021 | B64: Normal | C64: Australia | D64: Ritchies IGA | E64: 1BN+ | F64: RITCHIES STORES PROPRIETARY LIMITED (61 005 041 814) | G64: https://modernslaveryregister.gov.au/statements/12021/ | H64: Food and beverages, agriculture and fishing
A65: 12020 | B65: Normal | C65: Australia | D65: TeamMoto Motorcycles, Mower Depot, Ultimate Motorbikes, Motor Cycle Accessories Supermarket, Morgan & Wacker, Cassons, Forbes & Davies (NZ) Limited | E65: 450-500M | F65: MOTORCYCLE HOLDINGS LIMITED (29 150 386 995) | G65: https://modernslaveryregister.gov.au/statements/12020/ | H65: Automotive, machinery and heavy electrical equipment
A66: 12017 | B66: Normal | C66: Australia | D66: Allambi Care | E66: 100-150M | F66: ALLAMBI CARE LIMITED (24 097 262 459) | G66: https://modernslaveryregister.gov.au/statements/12017/ | H66: Charitable / not-for-profit activities
A67: 12015 | B67: Joint | C67: Australia | D67: HenderCare, HenderCare Foundation, Entree Early Years Recruitment, Hender Motors, Hender Careers, Hender IT, Wine Recruiters, Entree Recruitment, Hender Contracting, Hender Consulting | E67: 0-99M | F67: Hendercare Foundation (80 139 328 662), HENDER, MARK HAMILTON (51 219 055 255), The Trustee for The HenderCare Trust (19 087 520 254) | G67: https://modernslaveryregister.gov.au/statements/12015/ | H67: Automotive, machinery and heavy electrical equipment Information technology and telecommunication Professional and administrative services and supplies, including legal, consulting and accounting services Education and research Healthcare and pharmaceuticals Charitable / not-for-profit activities
A68: 11953 | B68: Joint | C68: Australia | E68: 300-350M | F68: CORDINA CHICKEN FARMS PTY LTD (29 003 058 428), CORDINA FOODS PTY LTD (17 002 429 825), SUMMERTIME CHICKEN PTY. LIMITED (66 000 852 586) | G68: https://modernslaveryregister.gov.au/statements/11953/ | H68: Food and beverages, agriculture and fishing
A69: 12014 | B69: Normal | C69: Australia | D69: Hills Health Solutions; Hills Technical Services | E69: 100-150M | F69: HILLS LIMITED (35 007 573 417) | G69: https://modernslaveryregister.gov.au/statements/12014/ | H69: Information technology and telecommunication Healthcare and pharmaceuticals
A70: 12013 | B70: Joint | C70: Australia | D70: LOVISA | E70: 1BN+ | F70: LOVISA AUSTRALIA PTY LTD, LOVISA HOLDINGS LIMITED (34 602 304 503), LOVISA PTY LIMITED (62 120 675 890) | G70: https://modernslaveryregister.gov.au/statements/12013/ | H70: Fashion, textiles, apparel and luxury goods | I70: California Transparency in Supply Chains Act 2010 Netherlands Child Labour Due Diligence Law 2019
A71: 12012 | B71: Normal | C71: Australia, New Zealand | D71: Hungry Jack's, Comgroup Supplies, Markwell, Seabest, Consolidated Foods, Competitive Foods, CFA, CFAL, Shore Mariner | E71: 1BN+ | F71: COMPETITIVE FOODS AUSTRALIA PTY LTD (48 010 542 908) | G71: https://modernslaveryregister.gov.au/statements/12012/ | H71: Food and beverages, agriculture and fishing
A72: 12011 | B72: Normal | C72: Australia | D72: Frutex, Spice Masters, Windsor Farm, Speedy Berry | E72: 150-200M | F72: The Trustee for FRUTEX TRUST AUSTRALIA (35 050 854 034) | G72: https://modernslaveryregister.gov.au/statements/12011/ | H72: Food and beverages, agriculture and fishing
A73: 11420 | B73: Joint | C73: Australia | E73: 1BN+ | F73: PEREGRINE ENERGY PTY LTD (80 615 822 065), RELIABLE PETROLEUM PTY LTD (54 602 197 375), SEPL Pty Ltd as trustee for SFT (75 492 874 033) | G73: https://modernslaveryregister.gov.au/statements/11420/ | H73: Food and beverages, agriculture and fishing Mining, metals, chemicals and resources (including oil and gas)
A74: 12009 | B74: Normal | C74: Australia | E74: 1BN+ | F74: DATA#3 LIMITED. (31 010 545 267) | G74: https://modernslaveryregister.gov.au/statements/12009/ | H74: Information technology and telecommunication
A75: 12005 | B75: Normal | C75: Australia | D75: Bank Australia Limited | E75: 150-200M | F75: BANK AUSTRALIA LIMITED (21 087 651 607) | G75: https://modernslaveryregister.gov.au/statements/12005/ | H75: Financial, insurance and real estate activities
A76: 12003 | B76: Normal | C76: Australia | D76: BSR Franchising, Betta Home Living, Designer Appliances, Furniture Zone, RT Edward, BSR Commercial, Stan Cash, Billy Guyatts | E76: 150-200M | F76: BSR Australia Limited (84 122 529 695) | G76: https://modernslaveryregister.gov.au/statements/12003/ | H76: Durable consumer goods, including electronics and appliances, home furnishings and other accessories
A77: 12002 | B77: Normal | C77: Australia | E77: 200-250M | F77: SYMBIO HOLDINGS LIMITED (37 118 699 853) | G77: https://modernslaveryregister.gov.au/statements/12002/ | H77: Information technology and telecommunication
A78: 11997 | B78: Joint | C78: Australia, United Kingdom, United States of America | D78: Good Goods Pty Ltd, Who Gives A Crap Inc, Who Gives A Crap Limited | E78: 150-200M | F78: GOOD GOODS PTY. LTD. (67 154 870 452) | G78: https://modernslaveryregister.gov.au/statements/11997/ | H78: Forestry, timber products, paper and containers and packaging | I78: United Kingdom Modern Slavery Act 2015
A79: 12000 | B79: Joint | C79: Australia | D79: Zenitas, Claro | E79: 0-99M | F79: GUARDIAN ALPHABET HOLDCO PTY LTD (54 628 455 103), GUARDIAN ALPHABET MIDCO PTY LTD (25 628 464 773), GUARDIAN ALPHABET PTY LTD (44 628 465 663), ZENITAS HEALTHCARE PTY LTD (78 009 074 588) | G79: https://modernslaveryregister.gov.au/statements/12000/ | H79: Healthcare and pharmaceuticals
A80: 11994 | B80: Joint | C80: Australia, Singapore, United Kingdom | E80: 150-200M | F80: INTERNATIONAL SOS (AUSTRALASIA) PTY. LTD. (83 052 247 104) | G80: https://modernslaveryregister.gov.au/statements/11994/ | H80: Healthcare and pharmaceuticals | I80: United Kingdom Modern Slavery Act 2015
A81: 11998 | B81: Joint | C81: Australia | D81: Booth's Hyundai, Booths Ford, Booth's Mitsubishi | E81: 100-150M | F81: E J & W A BOOTH PTY LTD (68 001 016 502) | G81: https://modernslaveryregister.gov.au/statements/11998/ | H81: Automotive, machinery and heavy electrical equipment
A82: 11996 | B82: Joint | C82: Australia | E82: 100-150M | F82: PROTEN PTY LIMITED (80 109 715 488) | G82: https://modernslaveryregister.gov.au/statements/11996/ | H82: Food and beverages, agriculture and fishing
A83: 11995 | B83: Joint | C83: Australia | E83: 200-250M | F83: PERKINS LADY JAN PTY. LTD. (57 064 110 247), PERKINS MARITIME PTY. LTD. (12 009 616 960), QGIF TAYLOR BIDCO PTY LTD (66 635 870 398), QGIF TAYLOR HOLDCO PTY LTD (55 635 867 999), SEA SWIFT (FINANCE) PTY. LIMITED (87 159 387 550), SEA SWIFT (HOLDINGS) PTY. LIMITED (49 159 387 390), Sea Swift International Services Pte. Ltd (93 133 094 334), SEA SWIFT (NT) PTY LTD (25 161 588 414), SEA SWIFT PTY. LTD. (16 010 889 040) | G83: https://modernslaveryregister.gov.au/statements/11995/ | H83: Transportation, logistics, and storage
A84: 11992 | B84: Normal | C84: Australia | E84: 350-400M | F84: COOGEE CHEMICALS PTY LTD (37 008 747 500) | G84: https://modernslaveryregister.gov.au/statements/11992/ | H84: Mining, metals, chemicals and resources (including oil and gas)
A85: 11989 | B85: Joint | C85: Australia | D85: Perth Radiological Clinic | E85: 500-600M | F85: GAMMA INVESTMENTS HOLDCO PTY LTD (30 635 098 690), M.P BLAKE & W.H BREIDAHL & S.J DAVIS & M.J FALLON & C FRAZER & R GREENBERGER & M MCCLOSKEY (33 714 762 652), PERTHRADCLINIC LTD (57 099 943 594) | G85: https://modernslaveryregister.gov.au/statements/11989/ | H85: Healthcare and pharmaceuticals
A86: 11990 | B86: Normal | C86: Australia | E86: 200-250M | F86: HENNING HARDERS (AUSTRALIA) PTY LTD (79 125 684 639) | G86: https://modernslaveryregister.gov.au/statements/11990/ | H86: Transportation, logistics, and storage
A87: 11986 | B87: Joint | C87: Australia | D87: Australian Footwear Pty Ltd, Cinori Shoes Pty Ltd, Colorado Group Sourcing Pty Ltd, Diana Ferrari Pty Ltd, Fusion Retail Brands Pty Ltd, MFG Shared Services Pty Ltd, Munro Mountfords Pty Ltd, Styletread Pty Ltd, Styling Services (NZ) Pty Ltd, Styling Services Pty Ltd, Munro Wanted Pty Ltd | E87: 350-400M | F87: MUNRO FOOTWEAR GROUP PTY LTD (59 614 250 501) | G87: https://modernslaveryregister.gov.au/statements/11986/ | H87: Fashion, textiles, apparel and luxury goods
A88: 11988 | B88: Joint | C88: Australia | D88: Lite n'Easy PTY LTD | E88: 100-150M | F88: LITE N' EASY PTY LTD (33 010 655 820) | G88: https://modernslaveryregister.gov.au/statements/11988/ | H88: Food and beverages, agriculture and fishing
A89: 11987 | B89: Joint | C89: Australia | D89: Harvey Norman, Space, The School Locker, Arisit, Poliform | E89: 1BN+ | F89: HARVEY NORMAN HOLDINGS LTD (54 003 237 545) | G89: https://modernslaveryregister.gov.au/statements/11987/ | H89: Durable consumer goods, including electronics and appliances, home furnishings and other accessories Other
A90: 11984 | B90: Normal | C90: Australia | D90: THE FRANK WHIDDON MASONIC HOMES OF NEW SOUTH WALES, THE WHIDDON GROUP, FRANK WHIDDON MASONIC HOMES OF NEW SOUTH WALES | E90: 150-200M | F90: THE FRANK WHIDDON MASONIC HOMES OF NEW SOUTH WALES (49 082 385 091) | G90: https://modernslaveryregister.gov.au/statements/11984/ | H90: Healthcare and pharmaceuticals Charitable / not-for-profit activities Other
A91: 11982 | B91: Normal | C91: Australia | E91: 100-150M | F91: TEAM MEDICAL SUPPLIES PTY LTD (30 150 132 504) | G91: https://modernslaveryregister.gov.au/statements/11982/ | H91: Healthcare and pharmaceuticals
A92: 11973 | B92: Joint | C92: Australia | D92: Uncle Bills (Australia) Pty Ltd, Uncle Bills Asia Pacific Pty Ltd, Uncle Bills (New Zealand) Ltd, Action Sports Equipment Pty Ltd | E92: 150-200M | F92: THE UBA GROUP PTY LTD (22 126 575 335) | G92: https://modernslaveryregister.gov.au/statements/11973/ | H92: Other
A93: 11977 | B93: Joint | C93: Australia | D93: Shaver Shop | E93: 600-700M | F93: Lavomer Riah Pty Ltd (78 150 747 676), SHAVER SHOP GROUP LIMITED (78 150 747 649), SHAVER SHOP PTY. LTD. (86 092 829 019) | G93: https://modernslaveryregister.gov.au/statements/11977/ | H93: Durable consumer goods, including electronics and appliances, home furnishings and other accessories Cosmetics and toiletries
A94: 11978 | B94: Joint | C94: Australia | E94: 300-350M | F94: ONEFORTYONE PLANTATIONS HOLDINGS NO. 2 PTY LTD (84 621 554 890), ONEFORTYONE PLANTATIONS HOLDINGS PTY LTD (42 159 689 942), ONEFORTYONE PLANTATIONS PTY LTD (38 159 689 988), ONEFORTYONE WOOD PRODUCTS PTY LTD (80 621 555 682) | G94: https://modernslaveryregister.gov.au/statements/11978/ | H94: Forestry, timber products, paper and containers and packaging
A95: 11979 | B95: Normal | C95: Australia | D95: DECJUBA, DECJUBA KIDS | E95: 200-250M | F95: DECJUBA PTY LTD (22 611 918 873) | G95: https://modernslaveryregister.gov.au/statements/11979/ | H95: Fashion, textiles, apparel and luxury goods | I95: United Kingdom Modern Slavery Act 2015
A96: 11975 | B96: Normal | C96: Australia | D96: Alfred Health | E96: 1BN+ | F96: Alfred Health (27 318 956 319) | G96: https://modernslaveryregister.gov.au/statements/11975/ | H96: Healthcare and pharmaceuticals
A97: 11842 | B97: Joint | C97: Australia | E97: 1BN+ | F97: AURIZON BULK CENTRAL FINANCE PTY LTD (24 615 317 130), AURIZON BULK CENTRAL HOLDINGS PTY LTD (53 132 989 998), AURIZON BULK CENTRAL NETWORK PTY LTD (92 144 081 774), AURIZON BULK CENTRAL PTY LTD (17 079 444 296), AURIZON BULK CENTRAL (SA HOLDINGS) PTY LTD (37 094 819 806), ONE RAIL AUSTRALIA (NSW) PTY LIMITED (11 079 546 777) | G97: https://modernslaveryregister.gov.au/statements/11842/ | H97: Transportation, logistics, and storage
A98: 11962 | B98: Normal | C98: Australia | D98: Fackelmann Housewares Pty Ltd, Fackelmann New Zealand Ltd, Fackelmann Housewares Singapore Pte Ltd, MCP Housewares HK Limited, Tomkin Australia Pty Ltd, Smart Brands Pty Ltd | E98: 100-150M | F98: AF ASIA-PACIFIC HOLDING PTY LTD (17 611 365 167) | G98: https://modernslaveryregister.gov.au/statements/11962/ | H98: Durable consumer goods, including electronics and appliances, home furnishings and other accessories
A99: 11972 | B99: Normal | C99: Australia | D99: Shaw and Partners Financial Planning Pty Limited | E99: 100-150M | F99: SHAW AND PARTNERS LIMITED (24 003 221 583) | G99: https://modernslaveryregister.gov.au/statements/11972/ | H99: Financial, insurance and real estate activities | I99: United Kingdom Modern Slavery Act 2015
A100: 11970 | B100: Normal | C100: Australia | D100: Hostplus | E100: 200-250M | F100: HOST-PLUS PTY. LIMITED (79 008 634 704) | G100: https://modernslaveryregister.gov.au/statements/11970/ | H100: Financial, insurance and real estate activities
...
